<?xml version="1.0" encoding="UTF-8"?><DataPerStep>
    <GlobalTime Time="20.85"/>
    <CrowdPos>
        <crowd v="{-0.2500750973; 0.000001063}" x="2.94" y="0.42" z="1"/>
        <crowd v="{-0.2491860673; 0.0144330012}" x="3.40" y="0.37" z="1"/>
        <crowd v="{-0.0419372748; 0.0356706962}" x="3.07" y="-0.02" z="1"/>
        <crowd v="{-0.0753694929; 0.0785556916}" x="3.56" y="-0.07" z="1"/>
        <crowd v="{-0.1052457143; 0.0779126599}" x="4.02" y="-0.02" z="1"/>
        <crowd v="{-0.2448700153; 0.000001063}" x="3.86" y="0.42" z="1"/>
        <crowd v="{-0.2047668241; 0.0324633353}" x="4.32" y="0.36" z="1"/>
        <crowd v="{-0.1509421279; -0.0131086576}" x="4.47" y="-0.10" z="1"/>
        <crowd v="{-0.1940165929; 0.000001063}" x="4.77" y="0.42" z="1"/>
        <crowd v="{-0.1386444235; -0.0031851153}" x="4.92" y="-0.11" z="1"/>
        <crowd v="{-0.1577172829; 0.0262666519}" x="5.23" y="0.37" z="1"/>
        <crowd v="{-0.0979142023; -0.0028496122}" x="5.37" y="-0.06" z="1"/>
        <crowd v="{-0.101664924; 0.0000007626}" x="5.68" y="0.42" z="1"/>
        <crowd v="{-0.0300926068; 0.034156404}" x="6.54" y="0.25" z="1"/>
        <crowd v="{-0.0456129209; -0.0024111074}" x="5.82" y="-0.12" z="1"/>
        <crowd v="{0.0272983118; 0.000001063}" x="2.29" y="1.07" z="1"/>
        <crowd v="{0.0431606019; 0.000001063}" x="2.78" y="1.07" z="1"/>
        <crowd v="{0.0450473318; 0.0242222617}" x="3.27" y="1.03" z="1"/>
        <crowd v="{0.0148337724; 0.000001063}" x="3.75" y="1.07" z="1"/>
        <crowd v="{-0.0240149437; -0.0450925885}" x="4.21" y="1.01" z="1"/>
        <crowd v="{-0.0878015654; 0.000001063}" x="4.66" y="1.07" z="1"/>
        <crowd v="{-0.1506512905; -0.0231409956}" x="5.09" y="0.97" z="1"/>
        <crowd v="{-0.2081971594; 0.000001063}" x="5.50" y="1.07" z="1"/>
        <crowd v="{-0.2346095011; -0.0016329126}" x="5.89" y="0.93" z="1"/>
        <crowd v="{-0.2379135959; 0.0000192191}" x="6.28" y="1.07" z="1"/>
        <crowd v="{-0.068128055; 0.0000289532}" x="6.14" y="0.42" z="1"/>
        <crowd v="{-0.0410669856; -0.0030120347}" x="6.81" y="-0.11" z="1"/>
        <crowd v="{-0.0063387836; -0.015989864}" x="6.27" y="-0.09" z="1"/>
        <crowd v="{0.2148687812; -0.0095688455}" x="9.99" y="-0.10" z="1"/>
        <crowd v="{-0.1776105428; 0.0395636787}" x="8.83" y="-0.05" z="1"/>
        <crowd v="{-0.0227906806; 0.000001063}" x="3.39" y="1.72" z="1"/>
        <crowd v="{-0.017257654; -0.0192544641}" x="3.84" y="1.62" z="1"/>
        <crowd v="{0.0088397222; 0.000001063}" x="4.27" y="1.72" z="1"/>
        <crowd v="{0.059587682; -0.0108682571}" x="4.68" y="1.60" z="1"/>
        <crowd v="{0.133838678; 0.000001063}" x="5.07" y="1.72" z="1"/>
        <crowd v="{0.2255649677; -0.0085070148}" x="5.43" y="1.60" z="1"/>
        <crowd v="{0.3153885513; 0.000001063}" x="5.76" y="1.72" z="1"/>
        <crowd v="{0.3837335527; -0.0053691403}" x="6.08" y="1.59" z="1"/>
        <crowd v="{0.4217903558; 0.000001063}" x="6.39" y="1.72" z="1"/>
        <crowd v="{0.4430898209; -0.0073006828}" x="6.72" y="1.59" z="1"/>
        <crowd v="{0.4684466179; 0.0000019372}" x="7.05" y="1.72" z="1"/>
        <crowd v="{0.383625966; -0.120295806}" x="7.38" y="1.55" z="1"/>
        <crowd v="{0.0150602204; 0.0033569506}" x="6.94" y="0.41" z="1"/>
        <crowd v="{0.0277493934; -0.0450024713}" x="7.20" y="0.08" z="1"/>
        <crowd v="{-0.2270698202; -0.000877613}" x="6.66" y="0.93" z="1"/>
        <crowd v="{-0.2395424765; -0.0556513419}" x="8.07" y="1.39" z="1"/>
        <crowd v="{-0.2283173043; 0.000001063}" x="1.69" y="2.37" z="1"/>
        <crowd v="{-0.2289640704; -0.0091791096}" x="2.13" y="2.25" z="1"/>
        <crowd v="{-0.2248726805; 0.000001063}" x="2.55" y="2.37" z="1"/>
        <crowd v="{-0.2139366671; -0.0075825491}" x="2.97" y="2.24" z="1"/>
        <crowd v="{-0.1963044599; 0.000001063}" x="3.39" y="2.37" z="1"/>
        <crowd v="{-0.1723110473; -0.0041231406}" x="3.80" y="2.24" z="1"/>
        <crowd v="{-0.1450776443; 0.000001063}" x="4.22" y="2.37" z="1"/>
        <crowd v="{-0.1152794057; -0.0002308331}" x="4.63" y="2.23" z="1"/>
        <crowd v="{-0.0855942661; 0.000001063}" x="5.05" y="2.37" z="1"/>
        <crowd v="{-0.054672018; -0.0000710281}" x="5.48" y="2.23" z="1"/>
        <crowd v="{-0.0139893554; 0.0000010002}" x="5.91" y="2.37" z="1"/>
        <crowd v="{0.071029465; 0.0623217784}" x="6.37" y="2.25" z="1"/>
        <crowd v="{-0.1903440575; -0.0034058048}" x="7.07" y="0.94" z="1"/>
        <crowd v="{0.0395953756; -0.0070940522}" x="7.38" y="0.49" z="1"/>
        <crowd v="{0.3510134425; -0.0613525992}" x="8.03" y="-0.01" z="1"/>
        <crowd v="{0.0643909089; 0.0828703922}" x="7.32" y="2.38" z="1"/>
        <crowd v="{0.1729180378; 0.000001063}" x="2.42" y="3.02" z="1"/>
        <crowd v="{0.4505811538; 0.0389239121}" x="3.01" y="2.95" z="1"/>
        <crowd v="{0.5567275192; 0.000001063}" x="3.60" y="3.02" z="1"/>
        <crowd v="{0.4621489685; 0.0387443728}" x="4.16" y="2.95" z="1"/>
        <crowd v="{0.3266838082; 0.0000010774}" x="4.66" y="3.02" z="1"/>
        <crowd v="{0.220909222; -0.0298742613}" x="5.12" y="2.94" z="1"/>
        <crowd v="{0.0994901226; 0.0000010721}" x="5.55" y="3.02" z="1"/>
        <crowd v="{0.0308562772; -0.0203302183}" x="5.97" y="2.92" z="1"/>
        <crowd v="{0.0449804728; -0.2818736541}" x="7.43" y="1.15" z="1"/>
        <crowd v="{-0.1456114807; -0.061617058}" x="7.90" y="0.40" z="1"/>
        <crowd v="{0.0997701243; 0.0046165655}" x="6.84" y="2.36" z="1"/>
        <crowd v="{0.161765042; -0.0712202039}" x="8.35" y="1.07" z="1"/>
        <crowd v="{-0.068884029; 0.0178067524}" x="7.88" y="1.10" z="1"/>
        <crowd v="{0.2841699233; 0.1194372399}" x="7.64" y="1.83" z="1"/>
        <crowd v="{-0.0178149281; 0.0742471353}" x="7.70" y="0.77" z="1"/>
        <crowd v="{0.2907412356; 0.0000212339}" x="9.77" y="4.32" z="1"/>
        <crowd v="{0.0862108415; 0.000001063}" x="2.88" y="3.67" z="1"/>
        <crowd v="{0.1864416913; 0.0397686092}" x="3.34" y="3.60" z="1"/>
        <crowd v="{0.2940541211; 0.000001063}" x="3.84" y="3.67" z="1"/>
        <crowd v="{0.2830120622; 0.0000010816}" x="4.34" y="3.67" z="1"/>
        <crowd v="{0.2141508462; -0.0087200223}" x="4.82" y="3.63" z="1"/>
        <crowd v="{0.1673338147; 0.0000009502}" x="5.29" y="3.67" z="1"/>
        <crowd v="{0.1177833222; -0.0378273103}" x="5.74" y="3.60" z="1"/>
        <crowd v="{0.0840449767; 0.0000002408}" x="6.19" y="3.67" z="1"/>
        <crowd v="{-0.0504719802; 0.41308984}" x="7.84" y="2.13" z="1"/>
        <crowd v="{0.0602753681; -0.0223540113}" x="6.63" y="3.57" z="1"/>
        <crowd v="{-0.0485954156; 0.0951813433}" x="7.55" y="2.77" z="1"/>
        <crowd v="{-0.023674011; -0.0242487316}" x="6.38" y="2.92" z="1"/>
        <crowd v="{-0.062318123; 0.0196920098}" x="6.79" y="2.98" z="1"/>
        <crowd v="{0.0801496373; 0.0048746591}" x="8.86" y="0.41" z="1"/>
        <crowd v="{0.0197517507; -0.0517959192}" x="8.14" y="3.30" z="1"/>
        <crowd v="{-0.0151541452; -0.1920823743}" x="7.69" y="4.42" z="1"/>
        <crowd v="{0.0971447088; 0.000001063}" x="4.90" y="4.32" z="1"/>
        <crowd v="{0.1424169826; -0.0217073898}" x="5.33" y="4.22" z="1"/>
        <crowd v="{0.2460632982; 0.0000010643}" x="5.72" y="4.32" z="1"/>
        <crowd v="{0.3324228849; -0.0148887549}" x="6.08" y="4.21" z="1"/>
        <crowd v="{0.3574967962; 0.0000009771}" x="6.43" y="4.32" z="1"/>
        <crowd v="{0.3301120514; 0.0000011384}" x="6.80" y="4.32" z="1"/>
        <crowd v="{0.2576765002; -0.0198972965}" x="7.15" y="4.18" z="1"/>
        <crowd v="{0.1507246465; -0.2086365025}" x="7.52" y="4.09" z="1"/>
        <crowd v="{0.0292940357; -0.0332040996}" x="7.08" y="3.59" z="1"/>
        <crowd v="{0.0079917999; -0.0882483336}" x="7.45" y="3.29" z="1"/>
        <crowd v="{-0.008350567; -0.122917109}" x="7.50" y="3.70" z="1"/>
        <crowd v="{-0.0762136825; -0.024213598}" x="8.84" y="3.57" z="1"/>
        <crowd v="{0.0040207096; 0.0000202974}" x="6.68" y="4.97" z="1"/>
        <crowd v="{-0.07971164; 0.0010774318}" x="7.20" y="2.97" z="1"/>
        <crowd v="{0.2290798731; -0.0011767119}" x="8.53" y="4.18" z="1"/>
        <crowd v="{0.0314824355; -0.2105958966}" x="7.68" y="5.83" z="1"/>
        <crowd v="{0.0010971265; 0.000001063}" x="1.47" y="4.97" z="1"/>
        <crowd v="{0.2312698281; 0.000001063}" x="2.02" y="4.97" z="1"/>
        <crowd v="{0.5105106908; 0.0186161124}" x="2.61" y="4.94" z="1"/>
        <crowd v="{0.7447538255; 0.000001063}" x="3.25" y="4.97" z="1"/>
        <crowd v="{0.8173309956; 0.0190849436}" x="3.88" y="4.93" z="1"/>
        <crowd v="{0.684734431; 0.000001063}" x="4.46" y="4.97" z="1"/>
        <crowd v="{0.4892152367; 0.000001063}" x="4.98" y="4.97" z="1"/>
        <crowd v="{0.3313932617; -0.0380662515}" x="5.46" y="4.90" z="1"/>
        <crowd v="{0.1397661986; 0.00000049}" x="5.88" y="4.97" z="1"/>
        <crowd v="{0.0978635613; -0.2064917896}" x="7.88" y="3.99" z="1"/>
        <crowd v="{0.0564296365; -0.0237577675}" x="6.29" y="4.87" z="1"/>
        <crowd v="{0.0331740857; 0.0590401464}" x="7.08" y="4.86" z="1"/>
        <crowd v="{0.0004376213; -0.2441139147}" x="7.43" y="5.54" z="1"/>
        <crowd v="{0.0431431244; -0.202791052}" x="7.77" y="5.35" z="1"/>
        <crowd v="{-0.1621617529; -0.2030748737}" x="8.05" y="5.10" z="1"/>
        <crowd v="{0.0925505324; 0.0971026504}" x="7.61" y="6.96" z="1"/>
        <crowd v="{0.3978657828; 0.000001063}" x="3.42" y="5.62" z="1"/>
        <crowd v="{0.3284401364; 0.000001063}" x="3.86" y="5.62" z="1"/>
        <crowd v="{0.2716435626; -0.0266669214}" x="4.26" y="5.53" z="1"/>
        <crowd v="{0.2114549766; 0.000001063}" x="4.66" y="5.62" z="1"/>
        <crowd v="{0.1508108495; -0.0164994652}" x="5.05" y="5.51" z="1"/>
        <crowd v="{0.1025552028; 0.000001063}" x="5.44" y="5.62" z="1"/>
        <crowd v="{0.0783076304; 0.000001063}" x="5.85" y="5.62" z="1"/>
        <crowd v="{0.0579053494; -0.0008794481}" x="6.24" y="5.48" z="1"/>
        <crowd v="{0.0147662969; 0.000001063}" x="6.64" y="5.62" z="1"/>
        <crowd v="{-0.0323564256; -0.002815391}" x="7.02" y="5.49" z="1"/>
        <crowd v="{-0.0111411014; -0.2387378445}" x="7.43" y="5.17" z="1"/>
        <crowd v="{-0.0304976457; -0.3396698822}" x="7.46" y="4.69" z="1"/>
        <crowd v="{-0.030567757; -0.004113585}" x="6.89" y="6.14" z="1"/>
        <crowd v="{0.0173110794; -0.2506630673}" x="8.15" y="5.45" z="1"/>
        <crowd v="{0.0651115053; -0.2417258881}" x="8.07" y="5.82" z="1"/>
        <crowd v="{0.0466769555; -0.0059546115}" x="6.11" y="6.14" z="1"/>
        <crowd v="{0.4255513725; 0.0893128283}" x="-0.34" y="6.75" z="1"/>
        <crowd v="{0.753874887; 0.0000003539}" x="0.07" y="6.27" z="1"/>
        <crowd v="{0.7553841126; 0.0583379104}" x="0.69" y="6.16" z="1"/>
        <crowd v="{0.5726889529; 0.0000029253}" x="1.25" y="6.27" z="1"/>
        <crowd v="{0.5500023586; 0.000001063}" x="1.84" y="6.27" z="1"/>
        <crowd v="{0.4092287849; -0.018707999}" x="2.32" y="6.16" z="1"/>
        <crowd v="{0.2427438851; 0.0000011492}" x="2.76" y="6.27" z="1"/>
        <crowd v="{0.1411967467; -0.0177227481}" x="3.17" y="6.16" z="1"/>
        <crowd v="{0.0717237655; 0.0000009784}" x="3.57" y="6.27" z="1"/>
        <crowd v="{0.0454210906; -0.014650551}" x="3.97" y="6.16" z="1"/>
        <crowd v="{0.0418434282; 0.0000007755}" x="4.38" y="6.27" z="1"/>
        <crowd v="{0.0633076121; 0.0000184975}" x="4.81" y="6.27" z="1"/>
        <crowd v="{0.0875027111; 0.000066049}" x="5.25" y="6.27" z="1"/>
        <crowd v="{0.0880495353; -0.0008810976}" x="5.67" y="6.13" z="1"/>
        <crowd v="{0.1040238187; -0.0295105822}" x="7.24" y="6.78" z="1"/>
        <crowd v="{0.1051132935; 0.0010919974}" x="8.50" y="7.57" z="1"/>
        <crowd v="{-0.1052776327; -0.0076054191}" x="1.84" y="8.09" z="1"/>
        <crowd v="{-0.264589713; 0.0000800729}" x="1.52" y="6.92" z="1"/>
        <crowd v="{-0.2632401331; 0.000000835}" x="1.97" y="6.92" z="1"/>
        <crowd v="{-0.2612020877; -0.0101679834}" x="2.41" y="6.80" z="1"/>
        <crowd v="{-0.253323001; 0.000001063}" x="2.83" y="6.92" z="1"/>
        <crowd v="{-0.2328176665; -0.0030520123}" x="3.25" y="6.79" z="1"/>
        <crowd v="{-0.1960776758; 0.000001063}" x="3.67" y="6.92" z="1"/>
        <crowd v="{-0.1405976162; -0.0025895952}" x="4.09" y="6.78" z="1"/>
        <crowd v="{-0.0719430219; 0.000001063}" x="4.50" y="6.92" z="1"/>
        <crowd v="{-0.0017810373; -0.0014750599}" x="4.91" y="6.78" z="1"/>
        <crowd v="{0.0575544084; 0.0000009671}" x="5.31" y="6.92" z="1"/>
        <crowd v="{0.0991401278; -0.0011182846}" x="5.70" y="6.78" z="1"/>
        <crowd v="{0.1193548967; 0.0007606831}" x="6.08" y="6.92" z="1"/>
        <crowd v="{0.1213526034; -0.0007707268}" x="6.47" y="6.78" z="1"/>
        <crowd v="{0.1602805524; 0.1137436661}" x="8.23" y="8.66" z="1"/>
        <crowd v="{0.1141462166; 0.2539109084}" x="7.85" y="8.55" z="1"/>
        <crowd v="{0.1197465798; 0.000001063}" x="3.13" y="7.57" z="1"/>
        <crowd v="{0.0720104562; -0.0339456765}" x="3.57" y="7.49" z="1"/>
        <crowd v="{0.0226029092; 0.000001063}" x="3.99" y="7.57" z="1"/>
        <crowd v="{-0.0134000901; 0.0007783308}" x="4.42" y="7.57" z="1"/>
        <crowd v="{-0.043571294; -0.0206664355}" x="4.82" y="7.47" z="1"/>
        <crowd v="{-0.0649554009; 0.000001063}" x="5.23" y="7.57" z="1"/>
        <crowd v="{-0.0854372399; -0.0085368891}" x="5.64" y="7.45" z="1"/>
        <crowd v="{-0.1083373104; 0.000001063}" x="6.05" y="7.57" z="1"/>
        <crowd v="{-0.120726515; -0.0005256123}" x="6.45" y="7.43" z="1"/>
        <crowd v="{-0.1091767991; 0.0000006929}" x="6.85" y="7.57" z="1"/>
        <crowd v="{-0.0621289204; 0.0008430025}" x="7.26" y="7.43" z="1"/>
        <crowd v="{0.1589804505; 0.3058108842}" x="7.71" y="8.98" z="1"/>
        <crowd v="{0.2346368459; 0.3715732041}" x="7.73" y="9.43" z="1"/>
        <crowd v="{0.20427259; 0.2071284489}" x="7.77" y="8.14" z="1"/>
        <crowd v="{-0.2956138202; -0.0712585986}" x="8.70" y="9.46" z="1"/>
        <crowd v="{0.158677202; -0.0030824961}" x="8.93" y="7.44" z="1"/>
        <crowd v="{-0.1140110405; 0.000001063}" x="2.29" y="8.22" z="1"/>
        <crowd v="{-0.108801646; 0.0260740951}" x="2.73" y="8.12" z="1"/>
        <crowd v="{-0.0935996944; 0.000001063}" x="3.19" y="8.22" z="1"/>
        <crowd v="{-0.081443959; 0.0380468343}" x="3.63" y="8.09" z="1"/>
        <crowd v="{-0.0384524531; 0.000001063}" x="4.07" y="8.22" z="1"/>
        <crowd v="{-0.0148667858; -0.0019676572}" x="4.51" y="8.08" z="1"/>
        <crowd v="{0.0221858518; 0.000001063}" x="4.94" y="8.22" z="1"/>
        <crowd v="{0.0482265959; -0.0015399039}" x="5.36" y="8.08" z="1"/>
        <crowd v="{0.0646242805; 0.0000011188}" x="5.77" y="8.22" z="1"/>
        <crowd v="{0.0942202556; -0.0010860898}" x="6.18" y="8.08" z="1"/>
        <crowd v="{0.1545332746; -0.0006036421}" x="6.62" y="8.08" z="1"/>
        <crowd v="{0.0383240515; 0.2643214722}" x="7.44" y="8.46" z="1"/>
        <crowd v="{0.2605560323; 0.0188833152}" x="7.06" y="8.21" z="1"/>
        <crowd v="{-0.0710759187; 0.000001063}" x="4.05" y="8.87" z="1"/>
        <crowd v="{-0.0422655429; -0.022927612}" x="4.49" y="8.77" z="1"/>
        <crowd v="{0.0348715812; 0.000001063}" x="4.90" y="8.87" z="1"/>
        <crowd v="{0.1203938566; -0.0145845044}" x="5.28" y="8.76" z="1"/>
        <crowd v="{0.1826957595; 0.000001063}" x="5.65" y="8.87" z="1"/>
        <crowd v="{0.221950075; -0.0092057945}" x="6.03" y="8.75" z="1"/>
        <crowd v="{0.235561503; 0.000001063}" x="6.43" y="8.87" z="1"/>
        <crowd v="{0.2246100919; -0.0731494023}" x="6.85" y="8.86" z="1"/>
        <crowd v="{0.232291428; 0.1244815534}" x="7.29" y="8.89" z="1"/>
        <crowd v="{0.1666410343; 0.000001063}" x="5.02" y="9.52" z="1"/>
        <crowd v="{0.1696579589; 0.0379732365}" x="5.49" y="9.45" z="1"/>
        <crowd v="{0.1570493383; 0.0000010715}" x="5.96" y="9.52" z="1"/>
        <crowd v="{0.129990584; 0.0000010757}" x="6.42" y="9.52" z="1"/>
        <crowd v="{0.1055689539; -0.0161171486}" x="6.86" y="9.41" z="1"/>
        <crowd v="{0.1192529957; 0.0441265456}" x="7.29" y="9.54" z="1"/>
        <crowd v="{0.2095634977; -0.0023591708}" x="7.59" y="-0.12" z="1"/>
        <crowd v="{0.1874767353; -0.0111554239}" x="8.72" y="0.95" z="1"/>
        <crowd v="{0.1566531595; 0.000001063}" x="9.10" y="1.07" z="1"/>
        <crowd v="{0.1009366832; 0.000001063}" x="9.50" y="1.07" z="1"/>
        <crowd v="{0.0260495471; -0.0240236826}" x="9.92" y="0.97" z="1"/>
        <crowd v="{0.0621203356; 0.1038955084}" x="8.42" y="0.22" z="1"/>
        <crowd v="{0.1857705957; 0.0020720009}" x="9.72" y="0.42" z="1"/>
        <crowd v="{-0.2017231972; -0.2159646122}" x="8.32" y="1.61" z="1"/>
        <crowd v="{-0.2080694299; -0.0159074486}" x="8.68" y="1.60" z="1"/>
        <crowd v="{-0.2404407312; 0.000001063}" x="9.02" y="1.72" z="1"/>
        <crowd v="{-0.2823280739; -0.0196389723}" x="9.36" y="1.62" z="1"/>
        <crowd v="{-0.285279777; 0.000001063}" x="9.72" y="1.72" z="1"/>
        <crowd v="{0.0000984024; -0.0664024566}" x="8.17" y="0.72" z="1"/>
        <crowd v="{-0.0073808111; 0.1672266969}" x="7.87" y="2.51" z="1"/>
        <crowd v="{0.1396084335; -0.024955601}" x="9.56" y="-0.07" z="1"/>
        <crowd v="{0.103663049; 0.0426042696}" x="9.30" y="0.28" z="1"/>
        <crowd v="{0.0370968378; -0.0560956791}" x="8.16" y="1.90" z="1"/>
        <crowd v="{0.0466555612; -0.0185988327}" x="8.68" y="2.26" z="1"/>
        <crowd v="{0.0344139775; 0.000001063}" x="9.08" y="2.37" z="1"/>
        <crowd v="{0.0256742138; -0.0056542389}" x="9.49" y="2.24" z="1"/>
        <crowd v="{0.0363403977; 0.000001063}" x="9.90" y="2.37" z="1"/>
        <crowd v="{0.0370259729; 0.1112779541}" x="8.11" y="2.83" z="1"/>
        <crowd v="{-0.0259082176; -0.1137775101}" x="7.72" y="1.43" z="1"/>
        <crowd v="{-0.0707581328; -0.0102030929}" x="9.30" y="2.90" z="1"/>
        <crowd v="{-0.0879424907; -0.0106216432}" x="9.71" y="2.90" z="1"/>
        <crowd v="{-0.05776313; 0.0000037841}" x="8.40" y="3.67" z="1"/>
        <crowd v="{0.0092927685; 0.0253101898}" x="8.49" y="2.97" z="1"/>
        <crowd v="{-0.0415385027; 0.001965244}" x="8.90" y="3.02" z="1"/>
        <crowd v="{0.0116728643; -0.0031878294}" x="8.28" y="2.39" z="1"/>
        <crowd v="{-0.1006992794; 0.0175715586}" x="9.28" y="3.64" z="1"/>
        <crowd v="{-0.1425556472; -0.0257587067}" x="9.70" y="3.58" z="1"/>
        <crowd v="{-0.0401736253; -0.0568980866}" x="8.21" y="6.68" z="1"/>
        <crowd v="{0.0444715382; -0.179494333}" x="8.09" y="4.31" z="1"/>
        <crowd v="{0.3124373479; -0.0173949015}" x="9.36" y="4.21" z="1"/>
        <crowd v="{0.0300232998; -0.0003741908}" x="7.80" y="3.09" z="1"/>
        <crowd v="{-0.068645194; -0.1744200408}" x="7.89" y="3.60" z="1"/>
        <crowd v="{-0.0136152103; 0.0001075416}" x="6.51" y="6.27" z="1"/>
        <crowd v="{-0.1074615269; -0.3170525676}" x="7.71" y="4.95" z="1"/>
        <crowd v="{0.3013253776; 0.0001182546}" x="8.95" y="4.32" z="1"/>
        <crowd v="{-0.0789401046; -0.2155598951}" x="7.93" y="4.67" z="1"/>
        <crowd v="{-0.1187977869; -0.1770657}" x="8.26" y="4.81" z="1"/>
        <crowd v="{-0.0753830637; -0.0007245213}" x="8.68" y="4.83" z="1"/>
        <crowd v="{-0.006013095; 0.000001063}" x="9.09" y="4.97" z="1"/>
        <crowd v="{0.0451026681; 0.000001063}" x="9.52" y="4.97" z="1"/>
        <crowd v="{0.0740803693; -0.0088795804}" x="9.95" y="4.85" z="1"/>
        <crowd v="{-0.2047095555; 0.3967269176}" x="7.81" y="7.33" z="1"/>
        <crowd v="{0.0408852107; -0.1326502606}" x="7.66" y="6.24" z="1"/>
        <crowd v="{-0.0063685653; 0.0225998141}" x="7.27" y="6.24" z="1"/>
        <crowd v="{0.0518321423; 0.0083996471}" x="8.54" y="5.60" z="1"/>
        <crowd v="{0.1297823816; -0.0021647938}" x="8.95" y="5.48" z="1"/>
        <crowd v="{0.1706331604; 0.0000010687}" x="9.36" y="5.62" z="1"/>
        <crowd v="{0.1687333673; -0.0049489077}" x="9.79" y="5.49" z="1"/>
        <crowd v="{-0.1354146507; 0.2385922833}" x="7.59" y="7.73" z="1"/>
        <crowd v="{0.2856121284; 0.1046345349}" x="8.21" y="8.03" z="1"/>
        <crowd v="{0.0948570188; 0.2430473457}" x="8.08" y="7.65" z="1"/>
        <crowd v="{0.0715892088; -0.2211157205}" x="8.04" y="6.20" z="1"/>
        <crowd v="{-0.0763628005; -0.0543161069}" x="7.82" y="6.60" z="1"/>
        <crowd v="{0.0737276097; 0.0385627758}" x="8.42" y="6.20" z="1"/>
        <crowd v="{0.0263168263; -0.017289117}" x="8.80" y="6.16" z="1"/>
        <crowd v="{-0.0705205268; 0.0000007576}" x="9.17" y="6.27" z="1"/>
        <crowd v="{-0.183141901; -0.0278964764}" x="9.57" y="6.18" z="1"/>
        <crowd v="{0.1136806138; 0.0000005939}" x="6.85" y="6.92" z="1"/>
        <crowd v="{-0.0213143309; 0.0618075221}" x="8.18" y="7.08" z="1"/>
        <crowd v="{0.2167692642; 0.0002388479}" x="9.36" y="7.57" z="1"/>
        <crowd v="{-0.0213599143; 0.0646639442}" x="8.67" y="6.80" z="1"/>
        <crowd v="{0.1088333116; 0.0000470076}" x="9.14" y="6.92" z="1"/>
        <crowd v="{0.1649990287; -0.0019720391}" x="9.59" y="6.78" z="1"/>
        <crowd v="{-0.3533080998; 0.6753953297}" x="7.79" y="9.98" z="1"/>
        <crowd v="{0.1982128291; 0.029295211}" x="8.60" y="8.17" z="1"/>
        <crowd v="{0.0324616709; 0.0378931852}" x="8.12" y="9.15" z="1"/>
        <crowd v="{-0.4920814755; 0.0006925169}" x="9.14" y="9.52" z="1"/>
        <crowd v="{0.2313574302; 0.0000003097}" x="9.82" y="7.57" z="1"/>
        <crowd v="{0.070535702; 0.000769642}" x="8.60" y="8.87" z="1"/>
        <crowd v="{-0.6873982535; 0.0434548859}" x="9.63" y="9.44" z="1"/>
        <crowd v="{0.1273694167; 0.0091016022}" x="9.03" y="8.20" z="1"/>
        <crowd v="{0.1028433716; 0.0000000521}" x="9.49" y="8.22" z="1"/>
        <crowd v="{0.1232884492; -0.0010962809}" x="9.92" y="8.08" z="1"/>
        <crowd v="{-0.2246337983; 0.1230188575}" x="8.28" y="9.55" z="1"/>
        <crowd v="{0.0193545443; -0.0170182438}" x="9.03" y="8.76" z="1"/>
        <crowd v="{-0.0272799726; -0.0162495443}" x="9.48" y="8.76" z="1"/>
        <crowd v="{-0.0362995865; 0.0000008274}" x="9.92" y="8.87" z="1"/>
    </CrowdPos>
</DataPerStep>
