<?xml version="1.0" encoding="UTF-8"?><DataPerStep>
    <GlobalTime Time="25.50"/>
    <CrowdPos>
        <crowd v="{-0.2544355249; 0.0000000948}" x="2.26" y="0.42" z="1"/>
        <crowd v="{-0.2496914591; 0.0148597651}" x="2.71" y="0.33" z="1"/>
        <crowd v="{-0.2522476918; -0.0234556671}" x="2.48" y="-0.08" z="1"/>
        <crowd v="{-0.2221990577; -0.0208115258}" x="2.98" y="-0.06" z="1"/>
        <crowd v="{-0.196466522; 0.0041170101}" x="3.44" y="-0.09" z="1"/>
        <crowd v="{-0.2172685602; 0.0000000948}" x="3.17" y="0.42" z="1"/>
        <crowd v="{-0.1840556844; 0.0396418226}" x="3.63" y="0.35" z="1"/>
        <crowd v="{-0.160781731; -0.0005670461}" x="3.90" y="-0.04" z="1"/>
        <crowd v="{-0.1453772241; 0.0000000948}" x="4.09" y="0.42" z="1"/>
        <crowd v="{-0.1410158921; -0.0239716182}" x="4.36" y="-0.08" z="1"/>
        <crowd v="{-0.138924978; 0.034698378}" x="4.54" y="0.35" z="1"/>
        <crowd v="{-0.1119030605; -0.0158710846}" x="4.82" y="-0.03" z="1"/>
        <crowd v="{-0.1327861892; 0.000000068}" x="5.00" y="0.42" z="1"/>
        <crowd v="{-0.211628965; 0.0149453352}" x="5.92" y="0.39" z="1"/>
        <crowd v="{-0.104584501; -0.0015721084}" x="5.26" y="-0.12" z="1"/>
        <crowd v="{0.5212483964; 0.0000000948}" x="2.43" y="1.07" z="1"/>
        <crowd v="{0.8798997363; 0.0000000948}" x="3.41" y="1.07" z="1"/>
        <crowd v="{0.6567691555; 0.0217371752}" x="4.05" y="1.03" z="1"/>
        <crowd v="{0.4956605598; 0.0000000948}" x="4.47" y="1.07" z="1"/>
        <crowd v="{0.3503606686; -0.0260193719}" x="4.81" y="0.98" z="1"/>
        <crowd v="{0.2291885049; 0.0000000948}" x="5.14" y="1.07" z="1"/>
        <crowd v="{0.1629984532; -0.0155709842}" x="5.46" y="0.96" z="1"/>
        <crowd v="{0.1502381388; 0.0000000948}" x="5.78" y="1.07" z="1"/>
        <crowd v="{0.1665214448; -0.0116974562}" x="6.12" y="0.95" z="1"/>
        <crowd v="{0.1684418031; 0.0000017145}" x="6.47" y="1.07" z="1"/>
        <crowd v="{-0.1350395491; 0.0000025828}" x="5.45" y="0.42" z="1"/>
        <crowd v="{-0.1199489083; -0.0007073484}" x="6.09" y="-0.12" z="1"/>
        <crowd v="{-0.1228167822; -0.0091598941}" x="5.68" y="0.03" z="1"/>
        <crowd v="{0.2571063158; 0.1142656346}" x="9.47" y="-0.00" z="1"/>
        <crowd v="{0.0708789968; 0.0000000948}" x="3.64" y="1.72" z="1"/>
        <crowd v="{0.070343085; -0.0212129155}" x="4.08" y="1.62" z="1"/>
        <crowd v="{0.0718917751; 0.0000000948}" x="4.52" y="1.72" z="1"/>
        <crowd v="{0.0610181812; -0.0194726044}" x="4.95" y="1.62" z="1"/>
        <crowd v="{0.0275003084; 0.0000000948}" x="5.37" y="1.72" z="1"/>
        <crowd v="{-0.0188783077; -0.0140481472}" x="5.77" y="1.61" z="1"/>
        <crowd v="{-0.0538414776; 0.0000000948}" x="6.17" y="1.72" z="1"/>
        <crowd v="{-0.0561267199; -0.0030860739}" x="6.56" y="1.59" z="1"/>
        <crowd v="{-0.0139646224; 0.0000000821}" x="6.95" y="1.72" z="1"/>
        <crowd v="{-0.0092845465; -0.0294167676}" x="7.42" y="1.24" z="1"/>
        <crowd v="{0.0479562589; -0.1979157564}" x="7.39" y="1.69" z="1"/>
        <crowd v="{-0.0314881785; -0.1836569583}" x="7.57" y="0.69" z="1"/>
        <crowd v="{-0.2002597411; 0.0002994599}" x="6.36" y="0.42" z="1"/>
        <crowd v="{-0.0855841705; -0.0222183083}" x="6.54" y="-0.08" z="1"/>
        <crowd v="{0.1006452321; -0.0100101189}" x="6.82" y="0.95" z="1"/>
        <crowd v="{0.0942784848; -0.1642178414}" x="8.18" y="0.57" z="1"/>
        <crowd v="{0.3799203831; 0.0000000948}" x="2.42" y="2.37" z="1"/>
        <crowd v="{0.3425793878; -0.0410082949}" x="2.86" y="2.31" z="1"/>
        <crowd v="{-0.0221913732; 0.0000000948}" x="3.26" y="2.37" z="1"/>
        <crowd v="{-0.086475297; -0.0176585619}" x="3.64" y="2.26" z="1"/>
        <crowd v="{-0.0906282782; 0.0000000948}" x="4.02" y="2.37" z="1"/>
        <crowd v="{-0.0259038214; -0.0119257157}" x="4.39" y="2.25" z="1"/>
        <crowd v="{0.0623260522; 0.0000000948}" x="4.74" y="2.37" z="1"/>
        <crowd v="{0.1221881823; -0.0080840205}" x="5.07" y="2.24" z="1"/>
        <crowd v="{0.138958791; 0.0000000948}" x="5.40" y="2.37" z="1"/>
        <crowd v="{0.1345933343; -0.0059627529}" x="5.72" y="2.24" z="1"/>
        <crowd v="{0.1330787772; 0.0000000892}" x="6.04" y="2.37" z="1"/>
        <crowd v="{0.1453510573; -0.0044645973}" x="6.39" y="2.24" z="1"/>
        <crowd v="{0.0263011612; -0.0182885491}" x="7.18" y="0.96" z="1"/>
        <crowd v="{-0.0991509211; 0.0646657054}" x="6.79" y="0.30" z="1"/>
        <crowd v="{0.4223722074; -0.0055615002}" x="9.08" y="-0.11" z="1"/>
        <crowd v="{0.1334141054; -0.1004368924}" x="7.17" y="2.32" z="1"/>
        <crowd v="{-0.3025326411; 0.0000000948}" x="3.04" y="3.02" z="1"/>
        <crowd v="{-0.2726051765; 0.0529993332}" x="3.49" y="2.92" z="1"/>
        <crowd v="{-0.2620391021; 0.0000000948}" x="3.95" y="3.02" z="1"/>
        <crowd v="{-0.2516743128; 0.0536672224}" x="4.40" y="2.92" z="1"/>
        <crowd v="{-0.2466212728; 0.0000000961}" x="4.84" y="3.02" z="1"/>
        <crowd v="{-0.2574273952; -0.0026649612}" x="5.27" y="2.88" z="1"/>
        <crowd v="{-0.2500209194; 0.0000000956}" x="5.70" y="3.02" z="1"/>
        <crowd v="{-0.2141439996; -0.001813576}" x="6.10" y="2.88" z="1"/>
        <crowd v="{-0.0920772328; 0.0690414175}" x="7.27" y="0.29" z="1"/>
        <crowd v="{0.4285660695; -0.0273742054}" x="8.68" y="-0.07" z="1"/>
        <crowd v="{0.1608666536; -0.0088092826}" x="6.78" y="2.25" z="1"/>
        <crowd v="{0.1325618444; -0.0349133658}" x="8.48" y="0.99" z="1"/>
        <crowd v="{0.2836340483; -0.0988547511}" x="8.38" y="0.20" z="1"/>
        <crowd v="{0.0551461629; -0.2378921192}" x="7.78" y="1.37" z="1"/>
        <crowd v="{0.3082064441; -0.0522447023}" x="8.05" y="-0.02" z="1"/>
        <crowd v="{-0.0241903137; 0.0000018942}" x="9.66" y="4.32" z="1"/>
        <crowd v="{-0.0879823577; 0.0000000948}" x="3.42" y="3.67" z="1"/>
        <crowd v="{-0.09531731; -0.0075214701}" x="3.86" y="3.54" z="1"/>
        <crowd v="{-0.1098757772; 0.0000000948}" x="4.29" y="3.67" z="1"/>
        <crowd v="{-0.1229276863; 0.0000000965}" x="4.73" y="3.67" z="1"/>
        <crowd v="{-0.1383499678; -0.004620738}" x="5.15" y="3.54" z="1"/>
        <crowd v="{-0.1605526023; 0.0000000848}" x="5.56" y="3.67" z="1"/>
        <crowd v="{-0.1911186281; -0.0033744203}" x="5.96" y="3.54" z="1"/>
        <crowd v="{-0.2124156953; 0.0000000215}" x="6.33" y="3.67" z="1"/>
        <crowd v="{0.0963583453; -0.1216031129}" x="8.22" y="1.80" z="1"/>
        <crowd v="{-0.1965833867; -0.0019941103}" x="6.69" y="3.53" z="1"/>
        <crowd v="{0.0685326315; -0.2415022724}" x="7.81" y="1.77" z="1"/>
        <crowd v="{-0.1522667456; -0.0021631306}" x="6.52" y="2.88" z="1"/>
        <crowd v="{-0.0573940294; 0.001756644}" x="6.91" y="3.02" z="1"/>
        <crowd v="{0.1864173347; 0.0004348485}" x="9.59" y="0.42" z="1"/>
        <crowd v="{0.058133418; -0.1244103469}" x="8.14" y="3.26" z="1"/>
        <crowd v="{0.0473915009; -0.27806632}" x="7.70" y="3.67" z="1"/>
        <crowd v="{0.1519363677; 0.0000000948}" x="4.72" y="4.32" z="1"/>
        <crowd v="{0.0823178571; -0.0372824199}" x="5.19" y="4.25" z="1"/>
        <crowd v="{-0.0242479224; 0.0000000949}" x="5.64" y="4.32" z="1"/>
        <crowd v="{-0.1531914823; -0.0246291201}" x="6.05" y="4.23" z="1"/>
        <crowd v="{-0.2525349789; 0.0000000872}" x="6.44" y="4.32" z="1"/>
        <crowd v="{-0.272676076; -0.0297615502}" x="6.81" y="4.24" z="1"/>
        <crowd v="{-0.0019807899; -0.2158503996}" x="7.43" y="3.88" z="1"/>
        <crowd v="{-0.1451031692; 0.0213695106}" x="7.39" y="3.51" z="1"/>
        <crowd v="{-0.1636290494; 0.0052499991}" x="7.05" y="3.66" z="1"/>
        <crowd v="{0.098400559; -0.2053753889}" x="7.53" y="2.09" z="1"/>
        <crowd v="{-0.040241474; -0.0288386839}" x="7.50" y="3.15" z="1"/>
        <crowd v="{0.1232111934; -0.0361079439}" x="8.39" y="3.60" z="1"/>
        <crowd v="{0.326130607; -0.0039086318}" x="7.88" y="4.98" z="1"/>
        <crowd v="{-0.0108819262; 0.0047636568}" x="7.27" y="2.87" z="1"/>
        <crowd v="{0.1430657322; -0.0077183232}" x="8.79" y="4.19" z="1"/>
        <crowd v="{-0.0728471448; -0.0394714857}" x="7.79" y="6.25" z="1"/>
        <crowd v="{-0.2489839889; 0.0000000948}" x="3.70" y="4.97" z="1"/>
        <crowd v="{-0.2170266793; 0.0000000948}" x="4.16" y="4.97" z="1"/>
        <crowd v="{-0.1644679478; 0.0576884312}" x="4.62" y="4.86" z="1"/>
        <crowd v="{-0.0752150027; 0.0000000948}" x="5.08" y="4.97" z="1"/>
        <crowd v="{-0.0286426342; 0.0638126799}" x="5.52" y="4.85" z="1"/>
        <crowd v="{0.0384069929; 0.0000000948}" x="5.97" y="4.97" z="1"/>
        <crowd v="{0.1116892093; 0.0000000948}" x="6.41" y="4.97" z="1"/>
        <crowd v="{0.1830903572; -0.0028156267}" x="6.81" y="4.84" z="1"/>
        <crowd v="{0.2554656824; 0.0000000761}" x="7.19" y="4.97" z="1"/>
        <crowd v="{0.0949535011; -0.2756578823}" x="7.79" y="3.34" z="1"/>
        <crowd v="{0.3033224965; -0.0467347321}" x="7.55" y="4.86" z="1"/>
        <crowd v="{-0.2073565437; -0.1473661216}" x="7.51" y="4.49" z="1"/>
        <crowd v="{-0.0539986255; 0.0262664422}" x="7.51" y="5.95" z="1"/>
        <crowd v="{0.102432262; -0.1717070542}" x="8.05" y="4.70" z="1"/>
        <crowd v="{0.0188999844; -0.1729616586}" x="8.16" y="4.41" z="1"/>
        <crowd v="{-0.0337195761; -0.1093482442}" x="7.48" y="7.28" z="1"/>
        <crowd v="{-0.1109731615; 0.0000000948}" x="3.13" y="5.62" z="1"/>
        <crowd v="{-0.1149495985; 0.0000000948}" x="3.60" y="5.62" z="1"/>
        <crowd v="{-0.1053795944; 0.0394033763}" x="4.06" y="5.55" z="1"/>
        <crowd v="{-0.0825166218; 0.0000000948}" x="4.52" y="5.62" z="1"/>
        <crowd v="{-0.0615536569; 0.04358557}" x="4.98" y="5.54" z="1"/>
        <crowd v="{-0.0588057445; 0.0000000948}" x="5.44" y="5.62" z="1"/>
        <crowd v="{-0.0668119634; 0.0000000948}" x="5.90" y="5.62" z="1"/>
        <crowd v="{-0.0760349622; -0.0029512594}" x="6.34" y="5.49" z="1"/>
        <crowd v="{-0.0936647925; 0.0000000948}" x="6.77" y="5.62" z="1"/>
        <crowd v="{-0.0910909726; 0.0142678957}" x="7.22" y="5.59" z="1"/>
        <crowd v="{-0.1022055094; -0.1477664318}" x="7.62" y="5.38" z="1"/>
        <crowd v="{-0.2368406965; -0.0648813654}" x="7.18" y="4.30" z="1"/>
        <crowd v="{0.242149396; 0.2261034349}" x="7.27" y="6.22" z="1"/>
        <crowd v="{0.1227628572; 0.1482961565}" x="8.10" y="5.31" z="1"/>
        <crowd v="{-0.2330730933; -0.1687277991}" x="7.82" y="5.75" z="1"/>
        <crowd v="{0.3195770142; -0.0005311866}" x="6.54" y="6.13" z="1"/>
        <crowd v="{0.5914023648; -0.0025595061}" x="1.11" y="6.78" z="1"/>
        <crowd v="{-0.144773615; 0.0000000316}" x="1.20" y="6.27" z="1"/>
        <crowd v="{-0.1409040788; -0.0026857228}" x="1.64" y="6.13" z="1"/>
        <crowd v="{-0.1295128305; 0.000000261}" x="2.08" y="6.27" z="1"/>
        <crowd v="{-0.1150782413; 0.0000000948}" x="2.53" y="6.27" z="1"/>
        <crowd v="{-0.1025369994; -0.0016688644}" x="2.95" y="6.13" z="1"/>
        <crowd v="{-0.0944164654; 0.0000001025}" x="3.37" y="6.27" z="1"/>
        <crowd v="{-0.0879387824; -0.0015809742}" x="3.78" y="6.13" z="1"/>
        <crowd v="{-0.0753937971; 0.0000000873}" x="4.19" y="6.27" z="1"/>
        <crowd v="{-0.0470968766; -0.001306916}" x="4.59" y="6.13" z="1"/>
        <crowd v="{0.0044083326; 0.0000000692}" x="4.97" y="6.27" z="1"/>
        <crowd v="{0.0782174403; 0.0000016501}" x="5.38" y="6.27" z="1"/>
        <crowd v="{0.1707721806; 0.000005892}" x="5.77" y="6.27" z="1"/>
        <crowd v="{0.2674266439; -0.0000785991}" x="6.14" y="6.13" z="1"/>
        <crowd v="{-0.2309083752; 0.0163238488}" x="7.30" y="6.89" z="1"/>
        <crowd v="{-0.0278347004; -0.0149054802}" x="8.60" y="7.46" z="1"/>
        <crowd v="{0.0489941371; 0.0282831193}" x="2.64" y="8.17" z="1"/>
        <crowd v="{0.4699677058; 0.000007143}" x="1.58" y="6.92" z="1"/>
        <crowd v="{0.3670319227; 0.0000000745}" x="2.05" y="6.92" z="1"/>
        <crowd v="{0.254391665; -0.031640359}" x="2.48" y="6.84" z="1"/>
        <crowd v="{0.1908561226; 0.0000000948}" x="2.90" y="6.92" z="1"/>
        <crowd v="{0.1395820182; -0.0316901881}" x="3.31" y="6.84" z="1"/>
        <crowd v="{0.0999971395; 0.0000000948}" x="3.72" y="6.92" z="1"/>
        <crowd v="{0.0674875275; -0.0236544539}" x="4.13" y="6.82" z="1"/>
        <crowd v="{0.0389331208; 0.0000000948}" x="4.53" y="6.92" z="1"/>
        <crowd v="{0.0159029873; -0.0147935225}" x="4.93" y="6.81" z="1"/>
        <crowd v="{-0.0047625075; 0.0000000863}" x="5.33" y="6.92" z="1"/>
        <crowd v="{-0.0208370924; -0.0079496121}" x="5.73" y="6.79" z="1"/>
        <crowd v="{-0.0386177224; 0.0000678574}" x="6.13" y="6.92" z="1"/>
        <crowd v="{-0.0702546759; -0.0000687534}" x="6.53" y="6.78" z="1"/>
        <crowd v="{0.0261965265; -0.008461711}" x="8.54" y="8.75" z="1"/>
        <crowd v="{0.0405047122; -0.036604914}" x="8.25" y="8.28" z="1"/>
        <crowd v="{-0.0177852688; 0.0000000948}" x="2.85" y="7.57" z="1"/>
        <crowd v="{-0.0271652314; -0.0291468955}" x="3.30" y="7.48" z="1"/>
        <crowd v="{-0.0483918817; 0.0000000948}" x="3.73" y="7.57" z="1"/>
        <crowd v="{-0.073473805; 0.0000694317}" x="4.16" y="7.57" z="1"/>
        <crowd v="{-0.1086406544; -0.0173892989}" x="4.57" y="7.46" z="1"/>
        <crowd v="{-0.1444592264; 0.0000000948}" x="4.97" y="7.57" z="1"/>
        <crowd v="{-0.1690505114; -0.0026888743}" x="5.36" y="7.43" z="1"/>
        <crowd v="{-0.1771001229; 0.0000000948}" x="5.75" y="7.57" z="1"/>
        <crowd v="{-0.1563977692; -0.0000468877}" x="6.15" y="7.43" z="1"/>
        <crowd v="{-0.1014099473; 0.0000000618}" x="6.55" y="7.57" z="1"/>
        <crowd v="{-0.0565285894; -0.0189001196}" x="6.99" y="7.46" z="1"/>
        <crowd v="{0.0693981583; 0.1038582361}" x="7.85" y="8.27" z="1"/>
        <crowd v="{-0.009995992; 0.063111856}" x="7.91" y="8.68" z="1"/>
        <crowd v="{-0.084806982; -0.0081074227}" x="7.94" y="7.85" z="1"/>
        <crowd v="{-0.0528692516; -0.008671146}" x="8.96" y="7.45" z="1"/>
        <crowd v="{0.0769465629; 0.0000000948}" x="3.08" y="8.22" z="1"/>
        <crowd v="{0.1269241663; -0.0267341827}" x="3.49" y="8.13" z="1"/>
        <crowd v="{0.166034302; 0.0000000948}" x="3.87" y="8.22" z="1"/>
        <crowd v="{0.1671538782; -0.0191166325}" x="4.23" y="8.12" z="1"/>
        <crowd v="{0.135039576; 0.0000000948}" x="4.58" y="8.22" z="1"/>
        <crowd v="{0.0967897049; -0.0083308376}" x="4.92" y="8.10" z="1"/>
        <crowd v="{0.0709780769; 0.0000000948}" x="5.26" y="8.22" z="1"/>
        <crowd v="{0.0640308637; -0.005176069}" x="5.61" y="8.09" z="1"/>
        <crowd v="{0.0636522993; 0.0000000998}" x="5.96" y="8.22" z="1"/>
        <crowd v="{0.0474067104; -0.0020386169}" x="6.33" y="8.08" z="1"/>
        <crowd v="{0.0024081479; -0.0018326541}" x="6.72" y="8.08" z="1"/>
        <crowd v="{0.1694295072; -0.0454353066}" x="7.55" y="8.01" z="1"/>
        <crowd v="{-0.0299286366; -0.0470288572}" x="7.10" y="8.17" z="1"/>
        <crowd v="{0.056197797; 0.0000000948}" x="4.52" y="8.87" z="1"/>
        <crowd v="{0.0577259507; 0.006480969}" x="4.97" y="8.76" z="1"/>
        <crowd v="{0.0518997689; 0.0000000948}" x="5.42" y="8.87" z="1"/>
        <crowd v="{0.0332854543; -0.0088782052}" x="5.85" y="8.75" z="1"/>
        <crowd v="{0.0169741292; 0.0000000948}" x="6.27" y="8.87" z="1"/>
        <crowd v="{0.0286137377; -0.0010644008}" x="6.67" y="8.73" z="1"/>
        <crowd v="{0.0737324317; 0.0000000926}" x="7.06" y="8.87" z="1"/>
        <crowd v="{-0.0133948119; -0.0386464026}" x="7.42" y="8.38" z="1"/>
        <crowd v="{0.1021408028; -0.0184054072}" x="7.48" y="8.79" z="1"/>
        <crowd v="{-0.4873186332; 0.0000000948}" x="4.83" y="9.52" z="1"/>
        <crowd v="{-0.429002149; -0.0045023724}" x="5.27" y="9.39" z="1"/>
        <crowd v="{-0.4754022414; 0.0000000956}" x="5.63" y="9.52" z="1"/>
        <crowd v="{-0.3702278109; 0.000000096}" x="6.04" y="9.52" z="1"/>
        <crowd v="{-0.1951593418; -0.0101216595}" x="6.46" y="9.40" z="1"/>
        <crowd v="{-0.0592263305; 0.0016798386}" x="6.92" y="9.52" z="1"/>
        <crowd v="{-0.0395561423; 0.0463552234}" x="7.01" y="-0.10" z="1"/>
        <crowd v="{0.0763241433; -0.0086439667}" x="8.93" y="0.95" z="1"/>
        <crowd v="{0.0649407576; 0.0000000948}" x="9.37" y="1.07" z="1"/>
        <crowd v="{0.0614992563; 0.0000000948}" x="9.83" y="1.07" z="1"/>
        <crowd v="{0.2197633825; -0.0262751244}" x="9.17" y="0.30" z="1"/>
        <crowd v="{-0.0094631253; -0.2280145954}" x="7.95" y="0.92" z="1"/>
        <crowd v="{0.0014956141; -0.2697494144}" x="8.17" y="1.28" z="1"/>
        <crowd v="{0.1127944889; -0.040559179}" x="8.61" y="1.66" z="1"/>
        <crowd v="{0.0760750946; -0.0167550476}" x="9.03" y="1.61" z="1"/>
        <crowd v="{0.0188254615; 0.0000000948}" x="9.45" y="1.72" z="1"/>
        <crowd v="{-0.0361792252; 0.0000000948}" x="9.89" y="1.72" z="1"/>
        <crowd v="{0.1906011518; 0.0080354038}" x="8.75" y="0.41" z="1"/>
        <crowd v="{0.0507788198; -0.2994407614}" x="8.13" y="2.16" z="1"/>
        <crowd v="{-0.1750650367; -0.0064647983}" x="9.99" y="-0.11" z="1"/>
        <crowd v="{-0.0144063859; 0.0417816398}" x="8.58" y="2.29" z="1"/>
        <crowd v="{0.1301517817; 0.0511992156}" x="9.53" y="2.28" z="1"/>
        <crowd v="{0.1571749775; 0.0000000948}" x="10.00" y="2.37" z="1"/>
        <crowd v="{-0.0681170144; -0.4736709292}" x="7.91" y="2.48" z="1"/>
        <crowd v="{0.1100570204; -0.2269124759}" x="7.84" y="0.33" z="1"/>
        <crowd v="{0.0360684343; 0.0082379769}" x="9.13" y="2.88" z="1"/>
        <crowd v="{0.0886821116; -0.0009475135}" x="9.59" y="2.88" z="1"/>
        <crowd v="{0.0766243308; 0.0070675568}" x="8.05" y="3.78" z="1"/>
        <crowd v="{0.1395597031; 0.0149418211}" x="8.29" y="2.92" z="1"/>
        <crowd v="{0.0307834283; 0.0001753114}" x="8.70" y="3.02" z="1"/>
        <crowd v="{0.0885202809; 0.0000449141}" x="9.06" y="2.37" z="1"/>
        <crowd v="{0.1418228709; 0.0015674872}" x="8.78" y="3.67" z="1"/>
        <crowd v="{0.1527723315; -0.0022978293}" x="9.17" y="3.53" z="1"/>
        <crowd v="{0.1534224449; 0.0000000968}" x="9.58" y="3.67" z="1"/>
        <crowd v="{-0.0821275297; -0.0595218185}" x="8.21" y="6.86" z="1"/>
        <crowd v="{-0.1468185674; -0.1019335953}" x="8.09" y="4.12" z="1"/>
        <crowd v="{0.0687829555; -0.0106352198}" x="9.36" y="4.20" z="1"/>
        <crowd v="{-0.0338153175; -0.127252807}" x="7.51" y="2.53" z="1"/>
        <crowd v="{-0.0789496575; -0.3830728803}" x="7.87" y="2.89" z="1"/>
        <crowd v="{-0.0919795033; 0.0000000166}" x="9.99" y="4.32" z="1"/>
        <crowd v="{0.2862376814; 0.0000142958}" x="6.90" y="6.27" z="1"/>
        <crowd v="{-0.0867045587; -0.0907985974}" x="7.83" y="4.34" z="1"/>
        <crowd v="{0.1322574611; 0.000010549}" x="9.08" y="4.32" z="1"/>
        <crowd v="{0.1219535167; -0.2408784608}" x="7.75" y="4.01" z="1"/>
        <crowd v="{0.1120058959; -0.0534337474}" x="8.48" y="4.28" z="1"/>
        <crowd v="{-0.0247063434; 0.0347722309}" x="8.32" y="4.94" z="1"/>
        <crowd v="{-0.0071870004; 0.0000000948}" x="8.70" y="4.97" z="1"/>
        <crowd v="{-0.0146685137; 0.0000000948}" x="9.08" y="4.97" z="1"/>
        <crowd v="{-0.0143564072; -0.0132660938}" x="9.48" y="4.85" z="1"/>
        <crowd v="{0.0157110609; 0.0000000948}" x="9.90" y="4.97" z="1"/>
        <crowd v="{-0.0286927668; -0.0808912316}" x="7.82" y="7.47" z="1"/>
        <crowd v="{0.0840517355; -0.0540243914}" x="7.80" y="6.67" z="1"/>
        <crowd v="{0.0770699023; 0.2240865466}" x="7.45" y="6.55" z="1"/>
        <crowd v="{-0.2258294038; 0.1101218214}" x="8.20" y="5.70" z="1"/>
        <crowd v="{-0.2964550689; -0.0173246565}" x="8.52" y="5.49" z="1"/>
        <crowd v="{-0.2505549775; 0.0000000953}" x="8.87" y="5.62" z="1"/>
        <crowd v="{-0.207822895; -0.0086596469}" x="9.21" y="5.50" z="1"/>
        <crowd v="{-0.1710678772; 0.0000000954}" x="9.55" y="5.62" z="1"/>
        <crowd v="{-0.1276994989; 0.0000000948}" x="9.92" y="5.62" z="1"/>
        <crowd v="{-0.0466034092; -0.0331529875}" x="7.40" y="7.66" z="1"/>
        <crowd v="{0.0082511408; -0.0152251329}" x="8.62" y="8.11" z="1"/>
        <crowd v="{-0.0276884996; -0.0082602146}" x="8.25" y="7.61" z="1"/>
        <crowd v="{0.0128953421; 0.0065730422}" x="8.18" y="6.09" z="1"/>
        <crowd v="{0.0230030941; -0.0983518653}" x="7.80" y="7.05" z="1"/>
        <crowd v="{0.0050330782; -0.070853235}" x="8.14" y="6.48" z="1"/>
        <crowd v="{-0.0257468626; -0.0008892374}" x="8.61" y="6.13" z="1"/>
        <crowd v="{0.0396794976; 0.0000000676}" x="9.01" y="6.27" z="1"/>
        <crowd v="{0.076212104; -0.0132685355}" x="9.41" y="6.15" z="1"/>
        <crowd v="{0.1172374725; 0.0000000883}" x="9.81" y="6.27" z="1"/>
        <crowd v="{-0.1366372331; 0.0000000457}" x="6.91" y="6.92" z="1"/>
        <crowd v="{0.0098241024; -0.0374897097}" x="8.14" y="7.24" z="1"/>
        <crowd v="{-0.100730523; 0.0000213067}" x="9.31" y="7.57" z="1"/>
        <crowd v="{-0.0786297695; -0.0289351214}" x="8.59" y="6.83" z="1"/>
        <crowd v="{-0.0776711616; 0.0000041934}" x="8.96" y="6.92" z="1"/>
        <crowd v="{-0.054438987; -0.0049833955}" x="9.32" y="6.79" z="1"/>
        <crowd v="{-0.0180792235; 0.0000000671}" x="9.70" y="6.92" z="1"/>
        <crowd v="{-0.0170336595; 0.0026133065}" x="9.01" y="8.22" z="1"/>
        <crowd v="{-0.0028766492; 0.0118312799}" x="8.17" y="9.02" z="1"/>
        <crowd v="{0.1213672411; 0.1604813522}" x="7.40" y="9.45" z="1"/>
        <crowd v="{-0.1307561292; 0.0000000276}" x="9.67" y="7.57" z="1"/>
        <crowd v="{0.0150957714; 0.0000686566}" x="8.98" y="8.87" z="1"/>
        <crowd v="{-0.0043736755; 0.0932489742}" x="7.75" y="9.14" z="1"/>
        <crowd v="{-0.0111362503; 0.0008119169}" x="9.40" y="8.22" z="1"/>
        <crowd v="{-0.0023910882; 0.0000000046}" x="9.79" y="8.22" z="1"/>
        <crowd v="{0.0893473394; 0.0411078403}" x="9.43" y="8.74" z="1"/>
        <crowd v="{0.1472308438; -0.0014495557}" x="9.88" y="8.73" z="1"/>
        <crowd v="{-0.0098486504; 0.9233078894}" x="7.76" y="9.87" z="1"/>
        <crowd v="{-0.3297749937; 0.2479895697}" x="8.18" y="9.52" z="1"/>
        <crowd v="{-0.2992490627; 0.0000161272}" x="8.64" y="9.52" z="1"/>
        <crowd v="{-0.2896744359; 0.0000000742}" x="9.10" y="9.52" z="1"/>
    </CrowdPos>
</DataPerStep>
