<?xml version="1.0" encoding="UTF-8"?><DataPerStep>
    <GlobalTime Time="47.25"/>
    <CrowdPos>
        <crowd v="{0.0002114675; 0.4114036866}" x="-0.43" y="3.42" z="1"/>
        <crowd v="{0.1801038477; 0.0013093855}" x="0.60" y="0.42" z="1"/>
        <crowd v="{0.2082089212; -0.0160883966}" x="0.38" y="0.01" z="1"/>
        <crowd v="{0.1875750521; -0.0060261205}" x="0.86" y="0.01" z="1"/>
        <crowd v="{0.1420262849; -0.0379156302}" x="1.33" y="-0.05" z="1"/>
        <crowd v="{0.1480038168; 0}" x="1.07" y="0.42" z="1"/>
        <crowd v="{0.1163948518; 0.0237880394}" x="1.53" y="0.38" z="1"/>
        <crowd v="{0.0716125808; 0.0351497514}" x="1.78" y="0.01" z="1"/>
        <crowd v="{0.0652083026; 0}" x="1.97" y="0.42" z="1"/>
        <crowd v="{0.0265460411; -0.0068587592}" x="2.20" y="-0.11" z="1"/>
        <crowd v="{0.0199676807; -0.0373548553}" x="2.39" y="0.28" z="1"/>
        <crowd v="{-0.1250654495; -0.0319331476}" x="2.94" y="-0.02" z="1"/>
        <crowd v="{-0.0153781008; 0}" x="2.79" y="0.42" z="1"/>
        <crowd v="{-0.0373935411; 0.001544028}" x="3.61" y="0.42" z="1"/>
        <crowd v="{-0.135114349; -0.0070284289}" x="3.39" y="0.02" z="1"/>
        <crowd v="{-0.2366531505; 0}" x="3.67" y="1.07" z="1"/>
        <crowd v="{-0.136858537; 0}" x="4.15" y="1.07" z="1"/>
        <crowd v="{0.0548593344; 0.0401104529}" x="4.66" y="1.00" z="1"/>
        <crowd v="{0.1945672621; 0}" x="5.20" y="1.07" z="1"/>
        <crowd v="{0.1887835221; 0.0464185684}" x="5.72" y="0.98" z="1"/>
        <crowd v="{0.0859511741; -0.0272951639}" x="6.22" y="0.98" z="1"/>
        <crowd v="{-0.0303786453; 0.0480216659}" x="6.71" y="0.33" z="1"/>
        <crowd v="{-0.0100785134; -0.0397738948}" x="7.84" y="-0.05" z="1"/>
        <crowd v="{-0.0793832664; 0.0000827592}" x="6.29" y="0.42" z="1"/>
        <crowd v="{0.0036538169; -0.0359426461}" x="6.68" y="1.00" z="1"/>
        <crowd v="{-0.0281120158; 0}" x="3.20" y="0.42" z="1"/>
        <crowd v="{-0.0620646381; -0.076650429}" x="4.00" y="0.33" z="1"/>
        <crowd v="{-0.1439979722; -0.0068833942}" x="3.80" y="-0.11" z="1"/>
        <crowd v="{0.1226783409; 0.0190561208}" x="9.87" y="0.23" z="1"/>
        <crowd v="{-0.5215242454; 0}" x="3.39" y="1.72" z="1"/>
        <crowd v="{-0.5099959609; -0.0085674306}" x="3.83" y="1.60" z="1"/>
        <crowd v="{-0.4723012741; 0}" x="4.26" y="1.72" z="1"/>
        <crowd v="{-0.4122811688; -0.0066289577}" x="4.68" y="1.59" z="1"/>
        <crowd v="{-0.3358013554; 0}" x="5.10" y="1.72" z="1"/>
        <crowd v="{-0.2462255752; -0.0048368301}" x="5.52" y="1.59" z="1"/>
        <crowd v="{-0.1480350179; 0}" x="5.93" y="1.72" z="1"/>
        <crowd v="{-0.0412347206; -0.0029138852}" x="6.35" y="1.59" z="1"/>
        <crowd v="{0.0695283775; 0.0564431351}" x="6.79" y="1.62" z="1"/>
        <crowd v="{0.0832862832; -0.020498292}" x="6.52" y="-0.08" z="1"/>
        <crowd v="{-0.0316337856; -0.0552494888}" x="7.13" y="1.03" z="1"/>
        <crowd v="{-0.0058840105; 0.0000001324}" x="5.86" y="0.42" z="1"/>
        <crowd v="{-0.0880023717; 0.0000000037}" x="4.38" y="0.42" z="1"/>
        <crowd v="{-0.0951901796; -0.0646457528}" x="4.21" y="-0.00" z="1"/>
        <crowd v="{-0.0564634782; 0.0041987064}" x="5.50" y="0.24" z="1"/>
        <crowd v="{0.0053489107; -0.0000110044}" x="8.61" y="0.29" z="1"/>
        <crowd v="{-0.0951868079; 0}" x="2.70" y="2.37" z="1"/>
        <crowd v="{-0.0721784685; -0.0290200279}" x="3.15" y="2.28" z="1"/>
        <crowd v="{-0.0031536512; 0}" x="3.59" y="2.37" z="1"/>
        <crowd v="{0.0816801142; -0.0106249537}" x="4.00" y="2.25" z="1"/>
        <crowd v="{0.1298411856; 0}" x="4.40" y="2.37" z="1"/>
        <crowd v="{0.1159509731; -0.007815115}" x="4.79" y="2.24" z="1"/>
        <crowd v="{0.0588180316; 0}" x="5.18" y="2.37" z="1"/>
        <crowd v="{0.0080899527; -0.0065273802}" x="5.57" y="2.24" z="1"/>
        <crowd v="{0.0044934787; 0}" x="5.95" y="2.37" z="1"/>
        <crowd v="{0.0509874391; -0.0045529775}" x="6.33" y="2.24" z="1"/>
        <crowd v="{0.1184041419; 0}" x="6.70" y="2.37" z="1"/>
        <crowd v="{0.1940845861; -0.0065634417}" x="7.07" y="2.23" z="1"/>
        <crowd v="{-0.1207762797; -0.0160132511}" x="5.28" y="-0.09" z="1"/>
        <crowd v="{-0.0990410973; 0.0000082134}" x="4.77" y="0.42" z="1"/>
        <crowd v="{0.0846656226; -0.000004095}" x="9.64" y="-0.12" z="1"/>
        <crowd v="{0.08172986; -0.3319195181}" x="7.56" y="1.17" z="1"/>
        <crowd v="{-0.3239931516; 0}" x="1.86" y="3.02" z="1"/>
        <crowd v="{-0.3251173915; -0.0051806536}" x="2.29" y="2.89" z="1"/>
        <crowd v="{-0.3241104339; 0}" x="2.73" y="3.02" z="1"/>
        <crowd v="{-0.3170809963; -0.0043191913}" x="3.16" y="2.89" z="1"/>
        <crowd v="{-0.2993991031; 0}" x="3.58" y="3.02" z="1"/>
        <crowd v="{-0.266055753; -0.0027113584}" x="4.01" y="2.89" z="1"/>
        <crowd v="{-0.2155647893; 0}" x="4.43" y="3.02" z="1"/>
        <crowd v="{-0.1495151684; -0.0016425754}" x="4.86" y="2.88" z="1"/>
        <crowd v="{-0.0832864579; 0.0001367022}" x="5.15" y="0.42" z="1"/>
        <crowd v="{0.0533374653; 0.0038223506}" x="9.27" y="0.07" z="1"/>
        <crowd v="{0.1431648384; -0.0579825389}" x="8.09" y="1.83" z="1"/>
        <crowd v="{-0.0441241377; 0.0399147007}" x="9.09" y="1.00" z="1"/>
        <crowd v="{0.0248894971; -0.0000125776}" x="8.89" y="-0.12" z="1"/>
        <crowd v="{-0.0037000646; -0.0371803866}" x="8.18" y="0.23" z="1"/>
        <crowd v="{0.0118709896; -0.0004793688}" x="8.45" y="-0.12" z="1"/>
        <crowd v="{0.0177882086; 0}" x="4.04" y="3.67" z="1"/>
        <crowd v="{0.0183566827; -0.0210057094}" x="4.49" y="3.57" z="1"/>
        <crowd v="{0.0358608311; 0}" x="4.92" y="3.67" z="1"/>
        <crowd v="{0.0829398745; 0}" x="5.35" y="3.67" z="1"/>
        <crowd v="{0.1487349494; -0.0096138939}" x="5.75" y="3.55" z="1"/>
        <crowd v="{0.2141325449; 0}" x="6.13" y="3.67" z="1"/>
        <crowd v="{0.2673625885; -0.0058608008}" x="6.50" y="3.54" z="1"/>
        <crowd v="{0.3023377911; 0}" x="6.86" y="3.67" z="1"/>
        <crowd v="{-0.0541673794; 0.0353206693}" x="8.61" y="1.00" z="1"/>
        <crowd v="{0.3137310422; -0.0143058024}" x="7.22" y="3.53" z="1"/>
        <crowd v="{-0.107533643; -0.1027528082}" x="7.05" y="0.07" z="1"/>
        <crowd v="{-0.0766966339; -0.0015404524}" x="5.31" y="2.88" z="1"/>
        <crowd v="{0.0047056576; 0.0000000216}" x="5.72" y="3.02" z="1"/>
        <crowd v="{0.2232334233; 0.1035831436}" x="8.24" y="3.48" z="1"/>
        <crowd v="{0.2807147516; -0.0014390286}" x="6.91" y="2.88" z="1"/>
        <crowd v="{-0.1200626903; 0}" x="4.08" y="4.32" z="1"/>
        <crowd v="{-0.1180699911; 0.0386400858}" x="4.56" y="4.25" z="1"/>
        <crowd v="{-0.13213531; 0}" x="5.02" y="4.32" z="1"/>
        <crowd v="{-0.1307348879; 0.006527572}" x="5.47" y="4.22" z="1"/>
        <crowd v="{-0.1239133353; 0}" x="5.92" y="4.32" z="1"/>
        <crowd v="{-0.1041469786; -0.0041681323}" x="6.36" y="4.19" z="1"/>
        <crowd v="{0.2725773434; 0.0827204321}" x="7.66" y="2.98" z="1"/>
        <crowd v="{0.3057179083; 0.0974376452}" x="7.28" y="3.03" z="1"/>
        <crowd v="{0.2780453022; -0.0217524475}" x="7.58" y="3.60" z="1"/>
        <crowd v="{0.1733402804; 0.154659371}" x="7.25" y="1.62" z="1"/>
        <crowd v="{0.1852138514; 0.0013034717}" x="6.53" y="3.02" z="1"/>
        <crowd v="{0.0450314177; -0.0029597233}" x="9.06" y="3.54" z="1"/>
        <crowd v="{0.0914902236; -0.000984279}" x="6.13" y="2.88" z="1"/>
        <crowd v="{0.0364024469; 0.2329322759}" x="7.84" y="3.86" z="1"/>
        <crowd v="{0.0932170281; 0.0587306928}" x="8.34" y="6.81" z="1"/>
        <crowd v="{-0.1450120601; 0}" x="5.76" y="4.97" z="1"/>
        <crowd v="{-0.1291462302; 0}" x="6.22" y="4.97" z="1"/>
        <crowd v="{-0.0863314318; -0.0022941301}" x="6.65" y="4.83" z="1"/>
        <crowd v="{-0.0315352818; 0.0097819387}" x="7.08" y="4.95" z="1"/>
        <crowd v="{0.0393882649; 0.1135775674}" x="7.54" y="5.43" z="1"/>
        <crowd v="{0.026843661; 0.1301956113}" x="7.76" y="5.80" z="1"/>
        <crowd v="{-0.0011637549; 0.0958385461}" x="7.53" y="4.99" z="1"/>
        <crowd v="{0.0477375679; 0.159058934}" x="7.61" y="4.56" z="1"/>
        <crowd v="{-0.1094386694; 0.1921950623}" x="7.96" y="5.11" z="1"/>
        <crowd v="{0.0685462009; -0.1624228896}" x="7.99" y="2.32" z="1"/>
        <crowd v="{0.0943276589; 0.3168378479}" x="7.60" y="4.16" z="1"/>
        <crowd v="{-0.0417240592; 0.0154910179}" x="7.21" y="4.29" z="1"/>
        <crowd v="{0.0902488007; 0.0055671263}" x="8.58" y="5.61" z="1"/>
        <crowd v="{0.1330193679; 0.1185255938}" x="7.85" y="3.34" z="1"/>
        <crowd v="{0.0086285623; 0.4100729657}" x="7.94" y="4.33" z="1"/>
        <crowd v="{0.1451420991; -0.0010934451}" x="6.87" y="7.43" z="1"/>
        <crowd v="{-0.1203347663; 0}" x="5.81" y="5.62" z="1"/>
        <crowd v="{-0.1035232253; 0}" x="6.27" y="5.62" z="1"/>
        <crowd v="{-0.0651802568; -0.007031468}" x="6.69" y="5.49" z="1"/>
        <crowd v="{-0.0297324859; 0.0206675089}" x="7.13" y="5.58" z="1"/>
        <crowd v="{0.0919465296; 0.1625332246}" x="7.56" y="6.16" z="1"/>
        <crowd v="{0.0579186652; 0.0342015021}" x="8.12" y="6.00" z="1"/>
        <crowd v="{0.0632463655; 0.0074252618}" x="8.07" y="6.39" z="1"/>
        <crowd v="{0.06332662; 0.0836112313}" x="8.13" y="5.52" z="1"/>
        <crowd v="{0.0980028191; 0.0329178971}" x="8.54" y="6.21" z="1"/>
        <crowd v="{0.2201435643; 0.0000062621}" x="8.89" y="4.97" z="1"/>
        <crowd v="{0.0646022883; 0.3073195546}" x="8.05" y="4.70" z="1"/>
        <crowd v="{-0.0721741065; 0.0000048015}" x="6.78" y="4.32" z="1"/>
        <crowd v="{0.1738766267; 0.1100040565}" x="7.65" y="6.95" z="1"/>
        <crowd v="{0.1917280316; 0.0575452924}" x="8.46" y="4.86" z="1"/>
        <crowd v="{0.2192568743; -0.0040496975}" x="9.32" y="4.84" z="1"/>
        <crowd v="{0.0390393358; 0.0001189484}" x="7.15" y="6.27" z="1"/>
        <crowd v="{-0.1820247092; -0.0000000361}" x="0.09" y="6.78" z="1"/>
        <crowd v="{0.4851438742; 0}" x="1.62" y="6.27" z="1"/>
        <crowd v="{0.4233019238; -0.0154405992}" x="2.08" y="6.16" z="1"/>
        <crowd v="{0.3623410527; 0}" x="2.53" y="6.27" z="1"/>
        <crowd v="{0.3146384763; 0}" x="2.98" y="6.27" z="1"/>
        <crowd v="{0.2702961656; 0.0000697509}" x="3.43" y="6.27" z="1"/>
        <crowd v="{0.2228419887; -0.0000486892}" x="3.85" y="6.13" z="1"/>
        <crowd v="{0.1806473237; 0.0187671875}" x="4.27" y="6.24" z="1"/>
        <crowd v="{0.1532244784; 0}" x="4.71" y="6.27" z="1"/>
        <crowd v="{0.1289855374; 0.0002796731}" x="5.14" y="6.27" z="1"/>
        <crowd v="{0.1010558317; -0.0002287709}" x="5.55" y="6.13" z="1"/>
        <crowd v="{0.0706336538; -0.0004408701}" x="5.97" y="6.13" z="1"/>
        <crowd v="{0.0442616664; 0.0000000001}" x="6.37" y="6.27" z="1"/>
        <crowd v="{0.0348977878; -0.0003596374}" x="6.76" y="6.13" z="1"/>
        <crowd v="{0.1474450918; 0.0037302929}" x="6.74" y="6.91" z="1"/>
        <crowd v="{-0.1978873111; 0.2463572912}" x="8.21" y="7.67" z="1"/>
        <crowd v="{0.1043155497; 0.0000003484}" x="1.94" y="8.22" z="1"/>
        <crowd v="{-0.1791017797; 0.0000000001}" x="0.53" y="6.92" z="1"/>
        <crowd v="{-0.1707913452; 0}" x="0.97" y="6.92" z="1"/>
        <crowd v="{-0.1578223791; -0.0027545903}" x="1.40" y="6.79" z="1"/>
        <crowd v="{-0.1412375819; 0}" x="1.82" y="6.92" z="1"/>
        <crowd v="{-0.1227897033; -0.0024862539}" x="2.24" y="6.78" z="1"/>
        <crowd v="{-0.104406077; 0}" x="2.67" y="6.92" z="1"/>
        <crowd v="{-0.0875357451; -0.0023956975}" x="3.10" y="6.78" z="1"/>
        <crowd v="{-0.0728418078; 0}" x="3.53" y="6.92" z="1"/>
        <crowd v="{-0.0579840974; -0.0015432698}" x="3.96" y="6.78" z="1"/>
        <crowd v="{-0.0381439841; 0}" x="4.39" y="6.92" z="1"/>
        <crowd v="{0.0087196735; -0.0000245641}" x="4.83" y="6.78" z="1"/>
        <crowd v="{0.1367491443; -0.0647499992}" x="5.30" y="6.90" z="1"/>
        <crowd v="{0.2359118532; 0.0555528745}" x="5.79" y="6.82" z="1"/>
        <crowd v="{-0.0698070787; 0}" x="1.39" y="7.57" z="1"/>
        <crowd v="{-0.0643811012; 0.0234976379}" x="1.84" y="7.47" z="1"/>
        <crowd v="{-0.0672380438; 0}" x="2.29" y="7.57" z="1"/>
        <crowd v="{-0.0771886519; 0.0000000009}" x="2.74" y="7.57" z="1"/>
        <crowd v="{-0.0903452517; -0.0044312649}" x="3.18" y="7.44" z="1"/>
        <crowd v="{-0.0964844964; 0}" x="3.61" y="7.57" z="1"/>
        <crowd v="{-0.0849300962; -0.0029392879}" x="4.03" y="7.44" z="1"/>
        <crowd v="{-0.0506720368; 0}" x="4.44" y="7.57" z="1"/>
        <crowd v="{0.0044945987; -0.0020969625}" x="4.86" y="7.43" z="1"/>
        <crowd v="{0.0704047351; 0}" x="5.26" y="7.57" z="1"/>
        <crowd v="{0.131377491; -0.0016327832}" x="5.67" y="7.43" z="1"/>
        <crowd v="{-0.3344536387; -0.0055281438}" x="8.57" y="7.43" z="1"/>
        <crowd v="{0.1147031793; 0}" x="2.39" y="8.22" z="1"/>
        <crowd v="{0.1250924782; -0.0344782839}" x="2.81" y="8.14" z="1"/>
        <crowd v="{0.1360759743; 0}" x="3.22" y="8.22" z="1"/>
        <crowd v="{0.1634187121; -0.0234664825}" x="3.64" y="8.12" z="1"/>
        <crowd v="{0.2156238273; 0}" x="4.08" y="8.22" z="1"/>
        <crowd v="{0.2974116254; 0.0454835522}" x="4.55" y="8.14" z="1"/>
        <crowd v="{0.2728494028; 0}" x="5.03" y="8.22" z="1"/>
        <crowd v="{0.228609886; -0.0396516861}" x="5.50" y="8.15" z="1"/>
        <crowd v="{0.1716608417; 0}" x="5.96" y="8.22" z="1"/>
        <crowd v="{0.1208001767; 0.02179556}" x="6.40" y="8.18" z="1"/>
        <crowd v="{0.1008981897; -0.0059596933}" x="6.83" y="8.09" z="1"/>
        <crowd v="{0.0956440493; 0.0697615377}" x="7.25" y="8.21" z="1"/>
        <crowd v="{0.3169415828; 0.1202636481}" x="7.30" y="8.89" z="1"/>
        <crowd v="{-0.1680290184; 1.4119503086}" x="8.10" y="9.96" z="1"/>
        <crowd v="{-0.1129704872; -0.0084292863}" x="4.59" y="-0.10" z="1"/>
        <crowd v="{-0.0233464786; 0.03841424}" x="9.58" y="1.00" z="1"/>
        <crowd v="{0.0906425987; 0.0000008283}" x="9.50" y="0.42" z="1"/>
        <crowd v="{-0.0358878475; -0.01635151}" x="5.72" y="-0.09" z="1"/>
        <crowd v="{0.0197292902; -0.0907727288}" x="6.10" y="0.05" z="1"/>
        <crowd v="{0.0053738128; -0.1986362039}" x="8.16" y="0.88" z="1"/>
        <crowd v="{0.0004572071; 0.0000727157}" x="8.41" y="1.58" z="1"/>
        <crowd v="{-0.0788399243; 0}" x="8.81" y="1.72" z="1"/>
        <crowd v="{-0.1141999187; 0}" x="9.24" y="1.72" z="1"/>
        <crowd v="{-0.1431129662; -0.026097659}" x="9.67" y="1.63" z="1"/>
        <crowd v="{0.0182299083; 0.0000221084}" x="9.02" y="0.42" z="1"/>
        <crowd v="{-0.0874065782; -0.1608386069}" x="7.47" y="0.20" z="1"/>
        <crowd v="{-0.0799684823; -0.1045145228}" x="7.87" y="0.55" z="1"/>
        <crowd v="{0.1500340759; -0.0007444923}" x="8.78" y="2.23" z="1"/>
        <crowd v="{0.1447942229; 0}" x="9.16" y="2.37" z="1"/>
        <crowd v="{0.1351355154; -0.0052297979}" x="9.54" y="2.24" z="1"/>
        <crowd v="{0.1272321192; 0}" x="9.94" y="2.37" z="1"/>
        <crowd v="{-0.0819549482; -0.1779034028}" x="7.45" y="0.64" z="1"/>
        <crowd v="{-0.1272368046; -0.0048249298}" x="4.93" y="0.08" z="1"/>
        <crowd v="{0.0666586121; -0.0003661001}" x="8.73" y="2.88" z="1"/>
        <crowd v="{0.0601061887; 0.0000146748}" x="9.11" y="3.02" z="1"/>
        <crowd v="{0.044404675; 0}" x="9.52" y="3.02" z="1"/>
        <crowd v="{-0.0005204683; 0}" x="9.94" y="3.02" z="1"/>
        <crowd v="{0.0842667478; 0.0003373535}" x="8.64" y="3.67" z="1"/>
        <crowd v="{0.1533140316; 0.0122702002}" x="8.00" y="2.83" z="1"/>
        <crowd v="{0.0964980095; -0.0275997178}" x="8.35" y="3.03" z="1"/>
        <crowd v="{0.1469539157; 0.0134789545}" x="8.38" y="2.23" z="1"/>
        <crowd v="{0.0129018074; 0.0000000193}" x="9.49" y="3.67" z="1"/>
        <crowd v="{0.0056449745; -0.0087910776}" x="9.93" y="3.55" z="1"/>
        <crowd v="{0.0583005815; 1.0579299828}" x="7.70" y="9.27" z="1"/>
        <crowd v="{0.0033827601; 0.4285381797}" x="8.17" y="4.03" z="1"/>
        <crowd v="{0.180289493; -0.0009468249}" x="9.68" y="4.18" z="1"/>
        <crowd v="{0.2365115414; -0.3464553985}" x="7.71" y="1.59" z="1"/>
        <crowd v="{0.1806088067; -0.1702571823}" x="8.04" y="1.31" z="1"/>
        <crowd v="{0.1342913015; 0.1399229686}" x="7.70" y="6.55" z="1"/>
        <crowd v="{0.3156197625; -0.192799865}" x="7.45" y="2.30" z="1"/>
        <crowd v="{0.3469684837; 0.0453962718}" x="8.48" y="4.24" z="1"/>
        <crowd v="{0.2055181247; -0.3515862597}" x="7.72" y="2.01" z="1"/>
        <crowd v="{0.1538763274; 0.0354006659}" x="7.70" y="2.60" z="1"/>
        <crowd v="{0.2963270333; 0.0085662035}" x="8.86" y="4.30" z="1"/>
        <crowd v="{0.2257994398; -0.0015405132}" x="9.26" y="4.18" z="1"/>
        <crowd v="{0.1762292482; 0.0000000222}" x="6.48" y="7.57" z="1"/>
        <crowd v="{0.1098444253; -0.0866428304}" x="7.19" y="6.85" z="1"/>
        <crowd v="{-0.0507198991; -0.0052998453}" x="7.53" y="7.31" z="1"/>
        <crowd v="{0.1994429583; 0.0001517457}" x="9.74" y="4.97" z="1"/>
        <crowd v="{0.1136886035; -0.0008857683}" x="9.49" y="5.48" z="1"/>
        <crowd v="{0.127196878; 0}" x="9.92" y="5.62" z="1"/>
        <crowd v="{0.1706937256; 0.0000000014}" x="6.07" y="7.57" z="1"/>
        <crowd v="{0.0266792003; 1.101466208}" x="7.90" y="8.78" z="1"/>
        <crowd v="{0.1060493101; 0.0222430015}" x="9.03" y="5.49" z="1"/>
        <crowd v="{0.0614660166; 0.0093843814}" x="7.24" y="7.57" z="1"/>
        <crowd v="{0.1139223711; 0.0001091904}" x="8.99" y="6.27" z="1"/>
        <crowd v="{0.0972509124; 0.0009690266}" x="9.45" y="6.22" z="1"/>
        <crowd v="{0.0711752599; 0.0000394949}" x="9.92" y="6.27" z="1"/>
        <crowd v="{0.207891947; 0}" x="6.27" y="6.92" z="1"/>
        <crowd v="{-0.1862757943; 0.1592516683}" x="7.82" y="7.57" z="1"/>
        <crowd v="{-0.2967692847; -0.003221015}" x="9.01" y="7.44" z="1"/>
        <crowd v="{0.1561683311; 0.16349636}" x="8.00" y="7.16" z="1"/>
        <crowd v="{0.1952894433; 0.28335771}" x="7.67" y="8.02" z="1"/>
        <crowd v="{0.1793482527; -0.0000825324}" x="8.81" y="6.78" z="1"/>
        <crowd v="{0.1920967517; 0}" x="9.24" y="6.92" z="1"/>
        <crowd v="{0.1905282308; -0.0035869005}" x="9.68" y="6.79" z="1"/>
        <crowd v="{-0.272144196; 0}" x="9.45" y="7.57" z="1"/>
        <crowd v="{-0.2406164738; 0.0588320644}" x="9.90" y="7.46" z="1"/>
        <crowd v="{-0.326285041; 0.3284222075}" x="8.21" y="8.32" z="1"/>
        <crowd v="{-0.3543924265; 0.0882008664}" x="8.69" y="8.14" z="1"/>
        <crowd v="{-0.1774291637; 0}" x="9.18" y="8.22" z="1"/>
        <crowd v="{-0.1096535494; 0}" x="9.66" y="8.22" z="1"/>
    </CrowdPos>
</DataPerStep>
