<?xml version="1.0" encoding="UTF-8"?><DataPerStep>
    <GlobalTime Time="68.70"/>
    <CrowdPos>
        <crowd v="{0.1518495131; 0.0000233126}" x="4.28" y="4.97" z="1"/>
        <crowd v="{0.0003947963; 0.5847586964}" x="-0.43" y="2.84" z="1"/>
        <crowd v="{-0.1771528578; -0.0177231174}" x="0.26" y="-0.08" z="1"/>
        <crowd v="{-0.1839272999; -0.0044877372}" x="0.71" y="-0.11" z="1"/>
        <crowd v="{-0.1905074861; -0.0164779156}" x="0.92" y="0.29" z="1"/>
        <crowd v="{-0.1116145287; 0.1219845925}" x="-0.38" y="0.51" z="1"/>
        <crowd v="{-0.1700677482; -0.0161980573}" x="0.04" y="0.33" z="1"/>
        <crowd v="{-0.1833851663; -0.0095236659}" x="1.17" y="-0.09" z="1"/>
        <crowd v="{-0.1761168738; 0}" x="0.49" y="0.42" z="1"/>
        <crowd v="{-0.1912448258; -0.0015880862}" x="1.61" y="-0.12" z="1"/>
        <crowd v="{-0.2049654818; 0.0000117575}" x="1.35" y="0.42" z="1"/>
        <crowd v="{-0.203811931; 0.0046033182}" x="2.03" y="0.04" z="1"/>
        <crowd v="{-0.2093766951; 0}" x="1.80" y="0.42" z="1"/>
        <crowd v="{-0.2027443771; 0.0000000222}" x="2.69" y="0.42" z="1"/>
        <crowd v="{-0.2101640414; 0.0075037783}" x="2.47" y="0.04" z="1"/>
        <crowd v="{-0.129733519; 0}" x="4.33" y="1.07" z="1"/>
        <crowd v="{-0.1114683804; 0}" x="4.78" y="1.07" z="1"/>
        <crowd v="{-0.071696545; -0.0155263747}" x="5.21" y="0.96" z="1"/>
        <crowd v="{-0.0332918435; 0}" x="5.63" y="1.07" z="1"/>
        <crowd v="{-0.0112338535; -0.0107713485}" x="6.05" y="0.95" z="1"/>
        <crowd v="{-0.0064630354; 0.0006018064}" x="6.46" y="1.07" z="1"/>
        <crowd v="{-0.135232807; 0.0035254793}" x="6.74" y="0.41" z="1"/>
        <crowd v="{-0.2298392454; -0.0000005726}" x="7.35" y="-0.12" z="1"/>
        <crowd v="{-0.1235804166; 0.0000000012}" x="6.29" y="0.42" z="1"/>
        <crowd v="{-0.0097422279; -0.0082648711}" x="6.88" y="0.95" z="1"/>
        <crowd v="{-0.2118362265; 0}" x="2.25" y="0.42" z="1"/>
        <crowd v="{-0.2037655557; -0.0033470386}" x="3.10" y="0.26" z="1"/>
        <crowd v="{-0.2139781331; -0.0000006746}" x="2.88" y="-0.12" z="1"/>
        <crowd v="{0.0555722238; -0.0069384882}" x="9.73" y="0.25" z="1"/>
        <crowd v="{-0.2157891446; 0}" x="4.27" y="1.72" z="1"/>
        <crowd v="{-0.1999287637; -0.0034383158}" x="4.72" y="1.61" z="1"/>
        <crowd v="{-0.1487479784; 0}" x="5.16" y="1.72" z="1"/>
        <crowd v="{-0.0750901234; -0.0110331009}" x="5.60" y="1.60" z="1"/>
        <crowd v="{0.0050836159; 0}" x="6.03" y="1.72" z="1"/>
        <crowd v="{0.0774202207; -0.0082332379}" x="6.45" y="1.60" z="1"/>
        <crowd v="{0.1317063073; 0.005606312}" x="6.85" y="1.71" z="1"/>
        <crowd v="{0.000598278; 0.0020605205}" x="7.42" y="0.59" z="1"/>
        <crowd v="{0.2715741794; -0.0096157201}" x="8.87" y="1.60" z="1"/>
        <crowd v="{-0.1166471596; -0.0000018631}" x="5.88" y="-0.12" z="1"/>
        <crowd v="{0.0893109433; -0.0911130641}" x="8.20" y="1.15" z="1"/>
        <crowd v="{-0.1701860297; 0}" x="5.23" y="0.42" z="1"/>
        <crowd v="{-0.2007023258; 0}" x="3.51" y="0.42" z="1"/>
        <crowd v="{-0.198441586; -0.0023944349}" x="3.34" y="-0.12" z="1"/>
        <crowd v="{-0.1811230321; -0.0071663354}" x="4.82" y="0.26" z="1"/>
        <crowd v="{0.0399684705; 0.0227755681}" x="8.55" y="0.26" z="1"/>
        <crowd v="{-0.2986450457; 0}" x="4.22" y="2.37" z="1"/>
        <crowd v="{-0.1129798441; 0.0524367348}" x="4.71" y="2.27" z="1"/>
        <crowd v="{0.1344050701; 0}" x="5.25" y="2.37" z="1"/>
        <crowd v="{0.3109896928; 0.0497813165}" x="5.80" y="2.28" z="1"/>
        <crowd v="{0.3005404116; 0}" x="6.34" y="2.37" z="1"/>
        <crowd v="{0.2036562553; 0.0422570614}" x="6.84" y="2.29" z="1"/>
        <crowd v="{0.1711645084; -0.0776807759}" x="7.64" y="1.63" z="1"/>
        <crowd v="{-0.0076716961; 0.0003998896}" x="7.30" y="1.08" z="1"/>
        <crowd v="{0.1436583055; -0.0154092398}" x="8.03" y="1.59" z="1"/>
        <crowd v="{0.1633959179; -0.025624798}" x="7.24" y="1.58" z="1"/>
        <crowd v="{-0.022989127; 0.0437181738}" x="7.73" y="1.17" z="1"/>
        <crowd v="{0.2360597765; 0.0023768991}" x="8.45" y="1.72" z="1"/>
        <crowd v="{-0.1756622071; -0.0000694263}" x="4.60" y="-0.12" z="1"/>
        <crowd v="{-0.1933883007; 0.0000000001}" x="3.95" y="0.42" z="1"/>
        <crowd v="{0.0625235929; -0.000031366}" x="9.53" y="-0.12" z="1"/>
        <crowd v="{-0.0479872308; -0.0727245737}" x="7.62" y="0.20" z="1"/>
        <crowd v="{-0.0385935348; 0}" x="5.27" y="3.02" z="1"/>
        <crowd v="{0.0608678552; 0.0598260314}" x="5.74" y="2.91" z="1"/>
        <crowd v="{0.1232416153; 0}" x="6.21" y="3.02" z="1"/>
        <crowd v="{0.1085927347; 0.0529123663}" x="6.67" y="2.92" z="1"/>
        <crowd v="{0.1147360701; -0.0790204148}" x="7.12" y="2.99" z="1"/>
        <crowd v="{0.1233048018; 0.0058198578}" x="7.56" y="2.88" z="1"/>
        <crowd v="{0.0659610635; -0.0337571073}" x="7.73" y="2.47" z="1"/>
        <crowd v="{0.1135242672; -0.0448132655}" x="8.00" y="2.87" z="1"/>
        <crowd v="{-0.1845823826; 0.000000002}" x="4.41" y="0.42" z="1"/>
        <crowd v="{0.0749008879; -0.003230251}" x="9.16" y="0.05" z="1"/>
        <crowd v="{0.1631214047; 0.0000123812}" x="8.96" y="2.37" z="1"/>
        <crowd v="{0.0701738896; -0.0000000002}" x="8.78" y="-0.12" z="1"/>
        <crowd v="{0.0011469556; 0.0026322916}" x="8.21" y="0.50" z="1"/>
        <crowd v="{0.0554022219; -0.0013976485}" x="8.37" y="-0.12" z="1"/>
        <crowd v="{0.0803574264; 0}" x="9.67" y="4.32" z="1"/>
        <crowd v="{0.3025259589; 0}" x="4.56" y="3.67" z="1"/>
        <crowd v="{0.2190024302; -0.0375759503}" x="5.01" y="3.60" z="1"/>
        <crowd v="{0.1543974077; 0}" x="5.44" y="3.67" z="1"/>
        <crowd v="{0.0990791938; 0}" x="5.87" y="3.67" z="1"/>
        <crowd v="{0.0411407387; -0.0189080806}" x="6.27" y="3.56" z="1"/>
        <crowd v="{-0.0026956846; 0}" x="6.66" y="3.67" z="1"/>
        <crowd v="{-0.0051450042; -0.0126640507}" x="7.05" y="3.55" z="1"/>
        <crowd v="{0.007818959; 0.0213500679}" x="7.41" y="3.78" z="1"/>
        <crowd v="{0.2351706414; -0.0093379989}" x="9.92" y="0.95" z="1"/>
        <crowd v="{-0.1023251002; -0.000002288}" x="6.34" y="-0.12" z="1"/>
        <crowd v="{0.0467857079; 0.0364322885}" x="8.49" y="2.95" z="1"/>
        <crowd v="{0.20565535; 0}" x="9.14" y="3.02" z="1"/>
        <crowd v="{0.1403426301; -0.1328057311}" x="7.31" y="2.28" z="1"/>
        <crowd v="{0.0350604965; 0}" x="6.01" y="4.32" z="1"/>
        <crowd v="{0.0369278454; -0.0043943862}" x="6.45" y="4.19" z="1"/>
        <crowd v="{0.0396324994; 0}" x="6.88" y="4.32" z="1"/>
        <crowd v="{0.0388398916; 0.0055522155}" x="7.30" y="4.19" z="1"/>
        <crowd v="{-0.009437723; 0.0962850682}" x="7.66" y="4.43" z="1"/>
        <crowd v="{0.048463193; 0.2293533391}" x="8.08" y="4.33" z="1"/>
        <crowd v="{-0.0084412585; 0.0709474617}" x="7.81" y="3.55" z="1"/>
        <crowd v="{0.0115326775; 0.0000025793}" x="8.43" y="3.67" z="1"/>
        <crowd v="{-0.1009688766; 0.1852949092}" x="7.92" y="4.76" z="1"/>
        <crowd v="{0.2532528387; 0.0000351468}" x="9.29" y="1.72" z="1"/>
        <crowd v="{-0.000464148; 0.0102827621}" x="7.43" y="3.31" z="1"/>
        <crowd v="{0.0286678034; 0.0000020596}" x="8.88" y="4.32" z="1"/>
        <crowd v="{0.1925745543; -0.0001270891}" x="9.58" y="2.88" z="1"/>
        <crowd v="{0.0036185739; -0.0252817909}" x="6.63" y="4.88" z="1"/>
        <crowd v="{0.1543941179; 0}" x="4.78" y="4.97" z="1"/>
        <crowd v="{0.106991456; 0}" x="5.27" y="4.97" z="1"/>
        <crowd v="{0.0728361414; -0.0275262321}" x="5.74" y="4.90" z="1"/>
        <crowd v="{0.0393294035; 0.0000094119}" x="6.19" y="4.97" z="1"/>
        <crowd v="{-0.0171116591; 0.0000049379}" x="5.52" y="5.62" z="1"/>
        <crowd v="{-0.1087170816; 0.0000680518}" x="5.78" y="6.27" z="1"/>
        <crowd v="{0.0863713117; 0.0000417837}" x="6.02" y="5.62" z="1"/>
        <crowd v="{0.0914350481; 0.0002297464}" x="6.51" y="5.62" z="1"/>
        <crowd v="{-0.1004243256; 0.0003480047}" x="6.24" y="6.27" z="1"/>
        <crowd v="{0.09228867; -0.0558494052}" x="8.17" y="2.46" z="1"/>
        <crowd v="{-0.0091412543; 0.2117424371}" x="7.86" y="5.19" z="1"/>
        <crowd v="{-0.0041733386; 0.0992519369}" x="7.78" y="3.99" z="1"/>
        <crowd v="{0.0633063632; 0.1727331051}" x="8.18" y="5.97" z="1"/>
        <crowd v="{0.0008121329; 0.024752727}" x="8.17" y="3.28" z="1"/>
        <crowd v="{-0.0893545532; 0.0266582056}" x="6.68" y="6.14" z="1"/>
        <crowd v="{0.2419755783; 0.0036341004}" x="9.91" y="7.56" z="1"/>
        <crowd v="{-0.2420555978; 0}" x="3.71" y="5.62" z="1"/>
        <crowd v="{-0.2354384821; 0}" x="4.17" y="5.62" z="1"/>
        <crowd v="{-0.2122679602; -0.0029132098}" x="4.60" y="5.49" z="1"/>
        <crowd v="{-0.1415126595; 0.0000002975}" x="5.04" y="5.62" z="1"/>
        <crowd v="{0.0295709449; -0.0034000104}" x="8.49" y="6.79" z="1"/>
        <crowd v="{0.1351391988; 0.0282411651}" x="8.55" y="6.22" z="1"/>
        <crowd v="{0.1168028244; 0.0532271932}" x="7.76" y="6.06" z="1"/>
        <crowd v="{-0.0922561109; 0.0169144943}" x="7.13" y="6.24" z="1"/>
        <crowd v="{0.136991745; -0.0027298384}" x="9.00" y="6.14" z="1"/>
        <crowd v="{0.0314112943; 0.0504350259}" x="7.84" y="5.63" z="1"/>
        <crowd v="{0.011541261; 0.0383241941}" x="7.40" y="5.73" z="1"/>
        <crowd v="{-0.0340479976; 0.1153455395}" x="7.51" y="4.86" z="1"/>
        <crowd v="{0.0481529215; 0.0385420817}" x="6.98" y="5.53" z="1"/>
        <crowd v="{-0.021092144; 0.0670563314}" x="7.43" y="5.29" z="1"/>
        <crowd v="{-0.0080815689; -0.0029192}" x="8.14" y="7.06" z="1"/>
        <crowd v="{0.038122408; 0.0000047192}" x="4.05" y="6.92" z="1"/>
        <crowd v="{0.0184396891; 0}" x="0.35" y="6.27" z="1"/>
        <crowd v="{-0.0010866032; -0.0000387453}" x="0.77" y="6.13" z="1"/>
        <crowd v="{-0.0352161447; 0}" x="1.18" y="6.27" z="1"/>
        <crowd v="{-0.065626614; 0}" x="1.60" y="6.27" z="1"/>
        <crowd v="{-0.1017213321; -0.0183085556}" x="2.00" y="6.16" z="1"/>
        <crowd v="{-0.1239760778; -0.0000000007}" x="2.41" y="6.13" z="1"/>
        <crowd v="{-0.1424383318; 0.0000002702}" x="2.81" y="6.27" z="1"/>
        <crowd v="{-0.1532849275; 0}" x="3.22" y="6.27" z="1"/>
        <crowd v="{-0.1566863308; 0.000000004}" x="3.64" y="6.27" z="1"/>
        <crowd v="{-0.1530830547; -0.0000000033}" x="4.04" y="6.13" z="1"/>
        <crowd v="{-0.144377746; -0.0000000063}" x="4.47" y="6.13" z="1"/>
        <crowd v="{-0.1324341563; 0.001062546}" x="4.89" y="6.27" z="1"/>
        <crowd v="{-0.1201856303; 0.0000230134}" x="5.33" y="6.27" z="1"/>
        <crowd v="{-0.0863208648; -0.0384742045}" x="7.55" y="6.43" z="1"/>
        <crowd v="{0.0396698213; 0}" x="7.00" y="8.22" z="1"/>
        <crowd v="{0.0325753734; 0}" x="4.51" y="6.92" z="1"/>
        <crowd v="{0.0211820819; 0}" x="4.96" y="6.92" z="1"/>
        <crowd v="{0.0105295492; -0.011986851}" x="5.39" y="6.80" z="1"/>
        <crowd v="{0.0062203399; 0}" x="5.82" y="6.92" z="1"/>
        <crowd v="{0.0006869056; -0.0016283161}" x="6.23" y="6.78" z="1"/>
        <crowd v="{-0.0135758531; 0}" x="6.65" y="6.92" z="1"/>
        <crowd v="{-0.0215332793; -0.0013387365}" x="7.06" y="6.78" z="1"/>
        <crowd v="{-0.0231303209; -0.0098580564}" x="7.42" y="7.02" z="1"/>
        <crowd v="{-0.0230353752; -0.0363381716}" x="7.79" y="6.79" z="1"/>
        <crowd v="{0.0470026504; 0.1013539572}" x="8.09" y="9.01" z="1"/>
        <crowd v="{0.0395780298; 0.0255832368}" x="8.10" y="6.44" z="1"/>
        <crowd v="{0.3523937189; 0}" x="5.11" y="7.57" z="1"/>
        <crowd v="{0.3165851144; 0.0325030993}" x="5.59" y="7.51" z="1"/>
        <crowd v="{0.2779571461; 0}" x="6.05" y="7.57" z="1"/>
        <crowd v="{0.2473410138; 0}" x="6.50" y="7.57" z="1"/>
        <crowd v="{0.2618988413; -0.0049549346}" x="6.93" y="7.44" z="1"/>
        <crowd v="{0.2718345176; 0.1067472045}" x="7.36" y="7.62" z="1"/>
        <crowd v="{0.1884524366; -0.0704879027}" x="7.74" y="7.36" z="1"/>
        <crowd v="{0.1497391607; -0.101103604}" x="7.85" y="7.85" z="1"/>
        <crowd v="{0.1978298751; 0.0201486166}" x="8.17" y="7.51" z="1"/>
        <crowd v="{0.2299361295; 0.0055467718}" x="8.61" y="7.56" z="1"/>
        <crowd v="{0.244961167; 0.0000790341}" x="9.06" y="7.57" z="1"/>
        <crowd v="{0.0317864136; 0.0215021002}" x="7.43" y="8.38" z="1"/>
        <crowd v="{0.0557184548; 0.0186964803}" x="7.72" y="8.74" z="1"/>
        <crowd v="{0.0014564628; 0.0297903735}" x="7.43" y="9.09" z="1"/>
        <crowd v="{0.0616550913; 0.072497396}" x="8.14" y="8.55" z="1"/>
        <crowd v="{0.0497037343; -0.0968653124}" x="8.01" y="9.69" z="1"/>
        <crowd v="{-0.0554995446; 0.107669928}" x="7.59" y="9.53" z="1"/>
        <crowd v="{0.2258970464; 0.0344398042}" x="8.38" y="9.38" z="1"/>
        <crowd v="{-0.1928903085; -0.0000157457}" x="3.78" y="-0.12" z="1"/>
        <crowd v="{0.0643423043; 0}" x="9.35" y="0.42" z="1"/>
        <crowd v="{-0.151567407; -0.0000002354}" x="5.04" y="-0.12" z="1"/>
        <crowd v="{-0.1354690334; -0.0015807103}" x="5.46" y="0.03" z="1"/>
        <crowd v="{0.0119987512; 0.061309616}" x="7.84" y="0.74" z="1"/>
        <crowd v="{0.2419196991; 0.0000367349}" x="9.75" y="1.72" z="1"/>
        <crowd v="{0.0604896592; 0.0000000003}" x="8.93" y="0.42" z="1"/>
        <crowd v="{-0.0854740871; 0.0108253698}" x="6.80" y="-0.07" z="1"/>
        <crowd v="{0.0360729762; -0.0000247477}" x="9.94" y="-0.12" z="1"/>
        <crowd v="{0.0272232178; -0.0354825251}" x="7.95" y="-0.05" z="1"/>
        <crowd v="{0.0342080363; -0.0378721296}" x="9.85" y="2.30" z="1"/>
        <crowd v="{-0.1190271664; 0.0921429078}" x="7.15" y="0.25" z="1"/>
        <crowd v="{-0.1841231185; -0.0058208787}" x="4.19" y="0.04" z="1"/>
        <crowd v="{0.0233014798; -0.0596350405}" x="7.68" y="2.04" z="1"/>
        <crowd v="{0.1421135006; -0.000000651}" x="9.57" y="3.53" z="1"/>
        <crowd v="{0.0726692264; 0.0000023101}" x="9.40" y="2.37" z="1"/>
        <crowd v="{-0.020695454; 0.0123661473}" x="7.07" y="4.95" z="1"/>
        <crowd v="{0.0613422274; -0.0004195866}" x="9.28" y="4.18" z="1"/>
        <crowd v="{0.2059513891; -0.0020326885}" x="9.06" y="0.93" z="1"/>
        <crowd v="{0.2288800101; 0.0000000522}" x="9.49" y="1.07" z="1"/>
        <crowd v="{0.1614954802; -0.0003143878}" x="8.55" y="2.23" z="1"/>
        <crowd v="{-0.0012930882; -0.0010093734}" x="8.48" y="4.18" z="1"/>
        <crowd v="{0.1642782424; -0.0075304936}" x="8.61" y="0.94" z="1"/>
        <crowd v="{0.0308652037; -0.0321683653}" x="8.08" y="1.98" z="1"/>
        <crowd v="{-0.0302445432; 0.0355736098}" x="8.29" y="4.98" z="1"/>
        <crowd v="{0.0271779115; 0.0000326437}" x="8.90" y="3.67" z="1"/>
        <crowd v="{-0.0658802545; 0.0009673862}" x="8.72" y="4.97" z="1"/>
        <crowd v="{-0.0676717544; -0.003348623}" x="9.15" y="4.84" z="1"/>
        <crowd v="{-0.0104781509; 0}" x="9.58" y="4.97" z="1"/>
        <crowd v="{0.1057059239; 0.0201535769}" x="8.25" y="8.07" z="1"/>
        <crowd v="{0.1093648107; 0.0970143384}" x="8.24" y="5.42" z="1"/>
        <crowd v="{0.0733580034; 0.0000068751}" x="9.15" y="5.62" z="1"/>
        <crowd v="{0.0838495008; -0.0000123908}" x="9.61" y="5.48" z="1"/>
        <crowd v="{0.2417049608; -0.0000158934}" x="9.48" y="7.43" z="1"/>
        <crowd v="{0.0757693752; 0.0317765478}" x="8.68" y="5.56" z="1"/>
        <crowd v="{0.1562185907; 0.0197188147}" x="8.70" y="8.18" z="1"/>
        <crowd v="{0.1309115028; 0.0000000016}" x="9.42" y="6.27" z="1"/>
        <crowd v="{0.1138602338; -0.0124400123}" x="9.86" y="6.15" z="1"/>
        <crowd v="{0.0221726801; 0.0102950203}" x="8.52" y="8.85" z="1"/>
        <crowd v="{0.2271375868; 0.0026744455}" x="9.16" y="8.22" z="1"/>
        <crowd v="{0.0509951381; 0}" x="8.91" y="6.92" z="1"/>
        <crowd v="{0.0383092593; -0.0077368005}" x="9.33" y="6.79" z="1"/>
        <crowd v="{0.0089158796; 0}" x="9.76" y="6.92" z="1"/>
        <crowd v="{0.2591361691; 0}" x="9.62" y="8.22" z="1"/>
    </CrowdPos>
</DataPerStep>
