<?xml version="1.0" encoding="UTF-8"?><DataPerStep>
    <GlobalTime Time="86.40"/>
    <CrowdPos>
        <crowd v="{0.1416530493; 0.0000000024}" x="6.26" y="4.97" z="1"/>
        <crowd v="{0.2464099277; 0.0002208916}" x="5.82" y="4.97" z="1"/>
        <crowd v="{0.3082872771; 0.0164418423}" x="1.73" y="-0.03" z="1"/>
        <crowd v="{0.3336000649; -0.0388450042}" x="2.17" y="-0.05" z="1"/>
        <crowd v="{0.0000338439; 0.4391097418}" x="-0.43" y="3.32" z="1"/>
        <crowd v="{1.1449090605; 0.023616603}" x="2.68" y="5.54" z="1"/>
        <crowd v="{1.034026835; 0.0088326371}" x="5.15" y="4.95" z="1"/>
        <crowd v="{0.3941751063; -0.011137007}" x="2.91" y="-0.10" z="1"/>
        <crowd v="{0.2406383416; 0.002243147}" x="5.38" y="1.07" z="1"/>
        <crowd v="{0.3739188778; -0.0408811179}" x="2.56" y="0.07" z="1"/>
        <crowd v="{0.3962493035; 0.0022381099}" x="1.84" y="0.42" z="1"/>
        <crowd v="{0.3814485609; -0.0450285361}" x="3.30" y="-0.04" z="1"/>
        <crowd v="{0.4046624476; 0}" x="2.30" y="0.42" z="1"/>
        <crowd v="{0.2872093749; 0}" x="3.16" y="0.42" z="1"/>
        <crowd v="{0.4323476509; 0.0470597012}" x="4.03" y="-0.04" z="1"/>
        <crowd v="{0.2186250102; 0}" x="5.84" y="1.07" z="1"/>
        <crowd v="{0.1935297558; 0}" x="6.29" y="1.07" z="1"/>
        <crowd v="{0.1693213056; -0.0114028712}" x="6.73" y="0.95" z="1"/>
        <crowd v="{0.1480272752; 0}" x="7.16" y="1.07" z="1"/>
        <crowd v="{0.1412252035; 0.0810782897}" x="7.59" y="1.00" z="1"/>
        <crowd v="{0.1209289987; 0.0466483418}" x="7.94" y="1.25" z="1"/>
        <crowd v="{0.3240195374; 0.0000007227}" x="7.12" y="0.42" z="1"/>
        <crowd v="{0.3481198303; -0.0006666065}" x="7.63" y="-0.12" z="1"/>
        <crowd v="{0.3228449617; 0}" x="6.72" y="0.42" z="1"/>
        <crowd v="{-0.0542545385; -0.0971334793}" x="8.23" y="0.92" z="1"/>
        <crowd v="{0.3024229654; 0}" x="2.75" y="0.42" z="1"/>
        <crowd v="{0.2959068609; 0.0163219802}" x="3.55" y="0.29" z="1"/>
        <crowd v="{0.4371338092; -0.001832024}" x="4.48" y="-0.01" z="1"/>
        <crowd v="{0.1628465096; -0.0964691357}" x="9.39" y="0.26" z="1"/>
        <crowd v="{0.1009391619; 0}" x="5.68" y="1.72" z="1"/>
        <crowd v="{0.1007807184; -0.0183101539}" x="6.12" y="1.61" z="1"/>
        <crowd v="{0.1073494251; 0}" x="6.55" y="1.72" z="1"/>
        <crowd v="{0.117539259; -0.0112955123}" x="6.97" y="1.60" z="1"/>
        <crowd v="{0.1196490742; -0.005997113}" x="7.38" y="1.69" z="1"/>
        <crowd v="{0.0511653041; 0.0471847053}" x="7.62" y="2.04" z="1"/>
        <crowd v="{0.068242353; 0.0002664131}" x="8.03" y="1.96" z="1"/>
        <crowd v="{0.0333358791; -0.2148671235}" x="8.19" y="0.44" z="1"/>
        <crowd v="{0.2916292469; -0.0425114072}" x="6.49" y="-0.04" z="1"/>
        <crowd v="{0.3417343435; 0}" x="5.92" y="0.42" z="1"/>
        <crowd v="{0.3244774802; 0}" x="3.95" y="0.42" z="1"/>
        <crowd v="{0.3948926822; -0.0154427004}" x="4.90" y="-0.09" z="1"/>
        <crowd v="{0.3410271171; 0.0074883978}" x="5.51" y="0.41" z="1"/>
        <crowd v="{-0.0528537966; -0.0040090987}" x="9.03" y="0.94" z="1"/>
        <crowd v="{-0.2709692513; 0}" x="6.55" y="2.37" z="1"/>
        <crowd v="{-0.2503696718; -0.0194594101}" x="6.99" y="2.27" z="1"/>
        <crowd v="{-0.1883807639; -0.0409789894}" x="7.41" y="2.41" z="1"/>
        <crowd v="{0.0552818683; -0.1416400592}" x="7.81" y="2.65" z="1"/>
        <crowd v="{0.04697914; 0.0345982994}" x="8.22" y="2.80" z="1"/>
        <crowd v="{0.1837178786; 0.009080446}" x="8.97" y="2.35" z="1"/>
        <crowd v="{0.2058441779; -0.0000168679}" x="8.69" y="1.58" z="1"/>
        <crowd v="{0.0930788511; -0.0141091849}" x="7.79" y="1.63" z="1"/>
        <crowd v="{0.1321868987; -0.0020444638}" x="9.52" y="1.58" z="1"/>
        <crowd v="{0.1976216421; -0.0443220442}" x="8.14" y="2.37" z="1"/>
        <crowd v="{0.1942223918; -0.0063516002}" x="8.26" y="1.59" z="1"/>
        <crowd v="{0.112030897; 0.0000002403}" x="9.94" y="1.72" z="1"/>
        <crowd v="{0.2717987335; -0.0227027678}" x="5.68" y="0.03" z="1"/>
        <crowd v="{0.3474576442; 0}" x="4.36" y="0.42" z="1"/>
        <crowd v="{0.0363473556; -0.0000000032}" x="9.20" y="-0.12" z="1"/>
        <crowd v="{0.1381514048; 0.0928868143}" x="7.82" y="0.64" z="1"/>
        <crowd v="{-0.143303381; 0}" x="4.54" y="3.02" z="1"/>
        <crowd v="{-0.0156965295; 0.0491218393}" x="5.03" y="2.93" z="1"/>
        <crowd v="{0.0737944629; 0}" x="5.53" y="3.02" z="1"/>
        <crowd v="{0.0885018651; 0.0452917668}" x="6.03" y="2.94" z="1"/>
        <crowd v="{0.0566702405; 0.0006758031}" x="6.51" y="3.02" z="1"/>
        <crowd v="{0.102887298; 0.000014584}" x="8.62" y="3.02" z="1"/>
        <crowd v="{0.1039659453; -0.0000009295}" x="9.27" y="2.88" z="1"/>
        <crowd v="{0.103963993; 0.000014595}" x="9.71" y="3.02" z="1"/>
        <crowd v="{0.3545852527; 0}" x="4.76" y="0.42" z="1"/>
        <crowd v="{0.1426646277; -0.00677655}" x="8.79" y="-0.11" z="1"/>
        <crowd v="{0.3450488698; 0.0227804235}" x="8.40" y="-0.03" z="1"/>
        <crowd v="{0.0207342837; 0.0001539866}" x="9.83" y="1.07" z="1"/>
        <crowd v="{0.2187652746; 0.0629874778}" x="8.61" y="0.30" z="1"/>
        <crowd v="{0.1020836948; 0}" x="5.27" y="3.67" z="1"/>
        <crowd v="{0.0430073124; -0.0253442186}" x="5.72" y="3.58" z="1"/>
        <crowd v="{0.0028514242; 0}" x="6.15" y="3.67" z="1"/>
        <crowd v="{-0.0098894719; 0}" x="6.59" y="3.67" z="1"/>
        <crowd v="{-0.0115130696; -0.0264239021}" x="7.02" y="3.58" z="1"/>
        <crowd v="{-0.0019194546; -0.1234627516}" x="7.43" y="2.88" z="1"/>
        <crowd v="{0.0278747011; 0.0250925542}" x="6.98" y="2.97" z="1"/>
        <crowd v="{0.0141085698; 0.0611786718}" x="8.15" y="3.24" z="1"/>
        <crowd v="{0.299686695; -0.0049994419}" x="6.90" y="-0.11" z="1"/>
        <crowd v="{0.0863237481; 0}" x="9.78" y="0.42" z="1"/>
        <crowd v="{0.1459745279; -0.0000005326}" x="9.41" y="2.23" z="1"/>
        <crowd v="{0.1119318257; 0}" x="6.39" y="4.32" z="1"/>
        <crowd v="{0.1203209567; 0.0397665471}" x="6.85" y="4.25" z="1"/>
        <crowd v="{0.1096462584; -0.0065292458}" x="7.30" y="4.18" z="1"/>
        <crowd v="{0.0012464772; -0.0531428}" x="7.43" y="3.75" z="1"/>
        <crowd v="{-0.0134053936; 0.0587542332}" x="7.84" y="3.55" z="1"/>
        <crowd v="{-0.041071689; 0.0153156628}" x="7.77" y="4.04" z="1"/>
        <crowd v="{-0.0118469808; 0.0477633468}" x="8.57" y="3.58" z="1"/>
        <crowd v="{0.167908244; 0.0000000003}" x="9.92" y="3.67" z="1"/>
        <crowd v="{0.1748261085; 0.0025025268}" x="8.58" y="4.97" z="1"/>
        <crowd v="{0.0600021326; 0.0364163323}" x="9.04" y="3.54" z="1"/>
        <crowd v="{0.0543738547; -0.0018388735}" x="9.37" y="4.18" z="1"/>
        <crowd v="{0.1885865033; -0.0315501761}" x="8.13" y="4.90" z="1"/>
        <crowd v="{0.1656774064; 0}" x="6.73" y="4.97" z="1"/>
        <crowd v="{0.1921987275; -0.050625537}" x="7.21" y="4.95" z="1"/>
        <crowd v="{0.1935636234; 0.0279881664}" x="7.68" y="4.92" z="1"/>
        <crowd v="{0.0664308692; 0.0355149115}" x="7.65" y="4.47" z="1"/>
        <crowd v="{0.0091417981; -0.0455492955}" x="7.96" y="5.79" z="1"/>
        <crowd v="{0.2163762906; 0.2137511096}" x="7.73" y="6.33" z="1"/>
        <crowd v="{0.0880774532; 0.0192743061}" x="8.52" y="6.88" z="1"/>
        <crowd v="{0.1094975968; -0.0011021896}" x="9.17" y="5.48" z="1"/>
        <crowd v="{0.0352457358; -0.0478046251}" x="7.52" y="5.76" z="1"/>
        <crowd v="{0.133158303; 0.0000000278}" x="9.84" y="2.37" z="1"/>
        <crowd v="{0.1098450478; 0.0000044849}" x="8.73" y="5.62" z="1"/>
        <crowd v="{-0.0127530514; 0.0706371402}" x="8.18" y="3.84" z="1"/>
        <crowd v="{-0.0167898416; -0.0573818661}" x="8.17" y="6.18" z="1"/>
        <crowd v="{0.1077956019; -0.0000274693}" x="9.50" y="3.53" z="1"/>
        <crowd v="{0.0673246183; 0.0037461263}" x="7.85" y="7.03" z="1"/>
        <crowd v="{0.1652510984; 0}" x="6.23" y="5.62" z="1"/>
        <crowd v="{0.1257791909; 0}" x="6.68" y="5.62" z="1"/>
        <crowd v="{0.0991787617; -0.0181659225}" x="7.12" y="5.56" z="1"/>
        <crowd v="{0.0681355706; -0.0315457921}" x="7.49" y="5.32" z="1"/>
        <crowd v="{-0.0488774717; 0.000002855}" x="8.60" y="6.27" z="1"/>
        <crowd v="{0.1036969304; 0.0035168738}" x="8.98" y="6.91" z="1"/>
        <crowd v="{-0.1660888384; 0.1906567359}" x="7.91" y="8.07" z="1"/>
        <crowd v="{-0.0717922156; -0.0039024845}" x="9.03" y="6.14" z="1"/>
        <crowd v="{0.0582326623; 0.0215775977}" x="8.12" y="6.66" z="1"/>
        <crowd v="{0.0637250236; 0.0131129531}" x="8.54" y="7.55" z="1"/>
        <crowd v="{0.0435582436; -0.0790579675}" x="7.47" y="3.31" z="1"/>
        <crowd v="{0.1088544706; 0.0000010836}" x="9.61" y="5.62" z="1"/>
        <crowd v="{0.2102326031; 0.1076103036}" x="8.23" y="5.42" z="1"/>
        <crowd v="{0.2487467859; 0.0000000005}" x="6.07" y="6.92" z="1"/>
        <crowd v="{0.0992270988; 0.0000001278}" x="2.05" y="6.27" z="1"/>
        <crowd v="{0.0980341681; 0.0018585718}" x="2.51" y="6.27" z="1"/>
        <crowd v="{0.0946493641; -0.0009843559}" x="2.94" y="6.13" z="1"/>
        <crowd v="{0.0923323946; 0.006600935}" x="3.37" y="6.26" z="1"/>
        <crowd v="{0.0979561506; -0.0000018509}" x="3.80" y="6.13" z="1"/>
        <crowd v="{0.1175042505; 0.0048508785}" x="4.23" y="6.26" z="1"/>
        <crowd v="{0.1536000525; 0}" x="4.68" y="6.27" z="1"/>
        <crowd v="{0.2016925937; 0}" x="5.13" y="6.27" z="1"/>
        <crowd v="{0.2506174925; 0}" x="5.58" y="6.27" z="1"/>
        <crowd v="{0.2899598747; -0}" x="6.01" y="6.13" z="1"/>
        <crowd v="{0.3079079832; -0}" x="6.46" y="6.13" z="1"/>
        <crowd v="{0.3014167881; 0.0020698439}" x="6.89" y="6.27" z="1"/>
        <crowd v="{0.290769678; 0.0585394531}" x="7.33" y="6.16" z="1"/>
        <crowd v="{-0.1138542083; 0.3117129217}" x="7.64" y="8.46" z="1"/>
        <crowd v="{0.1501230411; 0.0146588863}" x="8.37" y="8.84" z="1"/>
        <crowd v="{0.2321401796; -0.0003227584}" x="6.54" y="6.78" z="1"/>
        <crowd v="{0.1871910645; -0.0006022741}" x="7.02" y="6.78" z="1"/>
        <crowd v="{0.0792718913; 0.1143469072}" x="7.40" y="7.03" z="1"/>
        <crowd v="{0.021626412; 0.1751476674}" x="7.84" y="7.62" z="1"/>
        <crowd v="{-0.0426203962; 0.1421488274}" x="8.17" y="7.33" z="1"/>
        <crowd v="{-0.0961605472; 0.0800625792}" x="7.47" y="7.93" z="1"/>
        <crowd v="{0.1386033855; 0.1430869881}" x="7.90" y="8.84" z="1"/>
        <crowd v="{0.2453270979; 0.0014816448}" x="8.99" y="7.57" z="1"/>
        <crowd v="{0.116317418; 0.0000887843}" x="9.59" y="6.92" z="1"/>
        <crowd v="{0.1400557319; 0.009471723}" x="8.83" y="8.85" z="1"/>
        <crowd v="{-0.4585109667; -0.0241657614}" x="8.01" y="9.48" z="1"/>
        <crowd v="{-0.3695825239; -0.000187304}" x="9.70" y="8.73" z="1"/>
        <crowd v="{0.0030942695; 0.0942882824}" x="8.17" y="8.44" z="1"/>
        <crowd v="{-0.2365091122; 0.1625737587}" x="7.60" y="9.87" z="1"/>
        <crowd v="{0.5654487661; 0.0004716984}" x="9.52" y="7.44" z="1"/>
        <crowd v="{-0.1129643616; -0.0488024952}" x="8.07" y="9.94" z="1"/>
        <crowd v="{-0.4730173136; 0.0002233509}" x="8.48" y="9.52" z="1"/>
        <crowd v="{0.3490282033; 0.0042669583}" x="5.14" y="0.26" z="1"/>
        <crowd v="{0.2238797933; 0.0006950201}" x="9.00" y="0.42" z="1"/>
        <crowd v="{0.2760120919; -0}" x="6.07" y="-0.12" z="1"/>
        <crowd v="{0.3343028742; -0.0269950916}" x="6.32" y="0.33" z="1"/>
        <crowd v="{-0.0786529865; 0.0004193049}" x="8.63" y="1.07" z="1"/>
        <crowd v="{-0.0191124417; 0.00268149}" x="9.42" y="1.07" z="1"/>
        <crowd v="{0.3179986592; -0.0163074629}" x="7.27" y="0.05" z="1"/>
        <crowd v="{0.0225324408; -0.0000000025}" x="9.63" y="-0.12" z="1"/>
        <crowd v="{0.3713762398; -0.013246454}" x="8.02" y="-0.10" z="1"/>
        <crowd v="{0.3326147175; -0.0298772093}" x="7.60" y="0.28" z="1"/>
        <crowd v="{0.3016194922; -0.0070870714}" x="5.30" y="-0.11" z="1"/>
        <crowd v="{0.2169239056; -0.0009931602}" x="8.55" y="2.23" z="1"/>
        <crowd v="{0.0635290964; -0.0181741277}" x="8.10" y="4.44" z="1"/>
        <crowd v="{0.0597125546; 0.000197233}" x="9.79" y="4.32" z="1"/>
        <crowd v="{0.0526041053; 0.0001540372}" x="8.94" y="4.32" z="1"/>
        <crowd v="{0.1640059984; 0.0005213402}" x="9.10" y="1.72" z="1"/>
        <crowd v="{0.058667321; -0.0331635928}" x="8.50" y="4.24" z="1"/>
        <crowd v="{0.1685868515; 0.0392644391}" x="9.03" y="4.87" z="1"/>
        <crowd v="{0.1786214927; 0.0016237318}" x="9.48" y="4.97" z="1"/>
        <crowd v="{0.1847835614; -0.00264881}" x="9.92" y="4.83" z="1"/>
        <crowd v="{-0.115056263; -0.0000000401}" x="8.48" y="8.08" z="1"/>
        <crowd v="{-0.1150570963; 0.0000019934}" x="8.92" y="8.22" z="1"/>
        <crowd v="{-0.0895055565; 0}" x="9.45" y="6.27" z="1"/>
        <crowd v="{-0.1024784882; 0.0002843471}" x="9.90" y="6.27" z="1"/>
        <crowd v="{-0.1188614815; 0.0000002704}" x="9.38" y="8.22" z="1"/>
        <crowd v="{-0.1195385848; 0}" x="9.84" y="8.22" z="1"/>
    </CrowdPos>
</DataPerStep>
